{"id": "A000374", "update_date": "2018-01-10", "biography_text": "ABRAHAM, Ralph, a Representative from Louisiana; born in Alto, Richland Parish, La., September 16, 1954; graduated from Mangham High School, Mangham, La., 1972; B.A., Louisiana State University, Baton Rouge, La., 1980; D.V.M., Louisiana State University School of Veterinary Medicine, Baton Rouge, La., 1980; M.D., Louisiana State University School of Medicine, New Orleans, La., 1994; Mississippi National Guard Special Forces, 1986-1989; flight instructor; general family practitioner; aviation medical examiner; elected as a Republican to the One Hundred Fourteenth and to the succeeding Congress (January 3, 2015-present).", "name": {"last": "Abraham", "first": "Ralph"}, "date_of_birth": {"month": 9, "day": 16, "year": 1954}, "place_of_birth": "Alto, Richland Parish, La.", "post_secondary_degrees": [{"degree": "B.A.", "year": 1980, "institution": "Louisiana State University, Baton Rouge, La."}, {"degree": "M.D.", "year": 1994, "institution": "Louisiana State University School of Medicine, New Orleans, La."}]}