{"id": "B000755", "update_date": "2018-02-20", "biography_text": "BRADY, Kevin Patrick, a Representative from Texas; born in Vermillion, Clay County, S. Dak., April 11, 1955; graduated from Rapid City Central High School, Rapid City, S. Dak; B.A., University of South Dakota, Vermillion, S. Dak., 1990; member of the Texas state house of representatives, 1990-1996; elected as a Republican to the One Hundred Fifth and to the ten succeeding Congresses (January 3, 1997-present); chair, Joint Economic Committee (One Hundred Thirteenth Congress); chair, Committee on Ways & Means (One Hundred Fourteenth and One Hundred Fifteenth Congresses); chair, Joint Committee on Taxation (One Hundred Fifteenth Congress).", "name": {"last": "Brady", "first": "Kevin", "middle": "Patrick"}, "date_of_birth": {"month": 4, "day": 11, "year": 1955}, "place_of_birth": "Vermillion, Clay County, S. Dak.", "post_secondary_degrees": [{"degree": "B.A.", "year": 1990, "institution": "University of South Dakota, Vermillion, S. Dak."}]}