{"id": "B000287", "update_date": "2018-01-10", "biography_text": "BECERRA, Xavier, a Representative from California; born in Sacramento, Sacramento County, Calif., January 26, 1958; B.A., Stanford University, Stanford, Calif., 1980; J.D., Stanford University, Stanford., Calif., 1984; lawyer, private practice; staff, California state senator Art Torres, 1986; deputy attorney general, Office of the Attorney General, State of California, 1987-1990; member of the California state assembly, 1990-1992; elected as a Democrat to the One Hundred Third and to the twelve succeeding Congresses until his resignation on January 24, 2017 (January 3, 1993-January 24, 2017); chair, House Democratic Caucus (One Hundred Thirteenth and One Hundred Fourteenth Congresses); attorney general of California, 2017-present.", "name": {"last": "Becerra", "first": "Xavier"}, "date_of_birth": {"month": "January", "day": "26", "year": "1958"}, "place_of_birth": "Sacramento, Sacramento County, Calif.", "post_secondary_degrees": [{"degree": "B.A.", "year": "1980", "institution": "Stanford University, Stanford, Calif."}, {"degree": "J.D.", "year": "1984", "institution": "Stanford University, Stanford., Calif."}]}