{"id": "B001297", "update_date": "2019-01-04", "biography_text": "BUCK, Kenneth Robert, a Representative from Colorado; born in Ossining, Westchester County, N.Y., February 16, 1959; graduated from Ossining High School, Ossining, N.Y., 1977; A.B., Princeton University, Princeton, N.J., 1981; J.D., University of Wyoming, Laramie, Wyo., 1985; business executive; staff, United States House of Representatives Select Committee to Investigate Covert Arms Transactions with Iran, 1986-1987; attorney, United States Department of Justice, 1987-1990; attorney, Office of the United States Attorney, District of Colorado, 1990-2002; Weld County Colorado, district attorney, 2005-2014; unsuccessful candidate for election to the United States Senate in 2010; elected as a Republican to the One Hundred Fourteenth and to the two succeeding Congresses (January 3, 2015-present). ", "name": {"last": "Buck", "first": "Kenneth", "middle": "Robert"}, "date_of_birth": {"month": 2, "day": 16, "year": 1959}, "place_of_birth": "Ossining, Westchester County, N.Y.", "post_secondary_degrees": [{"degree": "A.B.", "year": 1981, "institution": "Princeton University, Princeton, N.J."}, {"degree": "J.D.", "year": 1985, "institution": "University of Wyoming, Laramie, Wyo."}]}