{"id": "B001293", "update_date": "2018-12-23", "biography_text": "BISHOP, Michael Dean, a Representative from Michigan; born in Almont, Lapeer County, Mich., March 18, 1967; graduated from Rochester Adams High School, Rochester Hills, Mich.; A.B., University of Michigan, Ann Arbor, Mich., 1989; J.D., Detroit College of Law (now Michigan State College of Law), East Lansing, Mich., 1993; lawyer, private practice; realtor; business owner; member of the Michigan state house of representatives, 1999-2002; member of the Michigan state senate, 2003-2010, majority leader, 2007-2010; unsuccessful candidate for nomination for Michigan state attorney general, 2010; unsuccessful candidate for election as Oakland County, Mich., prosecutor, 2012; elected as a Republican to the One Hundred Fourteenth and to the succeeding Congress (January 3, 2015-present).", "name": {"last": "Bishop", "first": "Michael", "middle": "Dean"}, "date_of_birth": {"month": 3, "day": 18, "year": 1967}, "place_of_birth": "Almont, Lapeer County, Mich.", "post_secondary_degrees": [{"degree": "A.B.", "year": 1989, "institution": "University of Michigan, Ann Arbor, Mich."}, {"degree": "J.D.", "year": 1993, "institution": "Detroit College of Law (now Michigan State College of Law), East Lansing, Mich."}]}