{"id": "B001299", "update_date": "2017-12-31", "biography_text": "BANKS, James E., a Representative from Indiana; born in Columbia City, Whitley County, Ind., July 16, 1979; graduated from Columbia City High School, Columbia City, Ind., 1997; B.A., Indiana University, Bloomington, Ind., 2004; M.B.A., Grace College and Seminary, Winona Lake, Ind., 2013; United States Navy Reserve, 2012-present, Afghanistan War Veteran, 2014-2015; commercial real estate broker; chairman, Whitley County, Ind., Republican Party, 2007-2011; member of the Whitley County, Ind. Council, 2008-2010; member of the Indiana state senate, 2010-2016; elected as a Republican to the One Hundred Fifteenth Congress (January 3, 2017-present).", "name": {"last": "Banks", "first": "James", "middle": "E."}, "date_of_birth": {"month": "July", "day": "16", "year": "1979"}, "place_of_birth": "Columbia City, Whitley County, Ind.", "post_secondary_degrees": [{"degree": "B.A.", "year": "2004", "institution": "Indiana University, Bloomington, Ind."}, {"degree": "M.B.A.", "year": "2013", "institution": "Grace College and Seminary, Winona Lake, Ind."}]}