{"id": "B001284", "update_date": "2018-12-23", "biography_text": "BROOKS, Susan, a Representative from Indiana; born in Auburn, Dekalb County, Ind., August 25, 1960; graduated from Homestead High School, Fort Wayne, Ind., 1978; B.A., Miami University, Oxford, Ohio, 1982; J.D., Indiana University, Indianapolis, Ind., 1985; lawyer, private practice; deputy mayor of Indianapolis, Ind., 1998-1999; United States attorney for the Southern District of Indiana, 2001-2007; senior vice president and general counsel, Ivy Tech Community College, Indianapolis, Ind.; elected as a Republican to the One Hundred Thirteenth and to the two succeeding Congresses (January 3, 2013-present); chair, Committee on Ethics (One Hundred Fifteenth Congress)", "name": {"last": "Brooks", "first": "Susan"}, "date_of_birth": {"month": 8, "day": 25, "year": 1960}, "place_of_birth": "Auburn, Dekalb County, Ind.", "post_secondary_degrees": [{"degree": "B.A.", "year": 1982, "institution": "Miami University, Oxford, Ohio"}, {"degree": "J.D.", "year": 1985, "institution": "Indiana University, Indianapolis, Ind."}]}