{"id": "B001288", "update_date": "2018-02-20", "biography_text": "BOOKER, Cory Anthony, a Senator from New Jersey; born on April 27, 1969, in Washington, D.C.; graduated Northern Valley Regional High School, Old Tappan, N.J., 1987; B.A., Stanford University, 1991; M.A., Stanford University, 1992; attended The Queen\u2019s College, University of Oxford, Oxford, England, as a Rhodes Scholar and received a graduate degree in 1994; J.D., Yale Law School, 1997; worked as an attorney in the non-profit sector; Newark City Council 1998-2002; Mayor of Newark, N.J. 2006-2013; elected as a Democrat to the United States Senate in a special election on October 16, 2013, to fill the vacancy caused by the death of Frank Lautenberg, a seat subsequently held by appointed senator Jeffrey Chiesa, and took the oath of office on October 31, 2013; reelected in 2014 for the term ending January 3, 2021.", "name": {"last": "Booker", "first": "Cory", "middle": "Anthony"}, "date_of_birth": {"month": 4, "day": 27, "year": 1969}, "place_of_birth": "", "post_secondary_degrees": [{"degree": "B.A.", "year": 1991, "institution": "Stanford University"}, {"degree": "M.A.", "year": 1992, "institution": "Stanford University"}, {"degree": "J.D.", "year": 1997, "institution": "Yale Law School"}]}