{"id": "B001251", "update_date": "2018-01-10", "biography_text": "BUTTERFIELD, George Kenneth, Jr. (G.K.), a Representative from North Carolina; born in Wilson, Wilson County, N.C., April 27, 1947; graduated from Charles H. Darden High School, Wilson, N.C.; B.A., North Carolina Central University, Durham, N.C., 1971; J.D., North Carolina Central University School of Law, 1974; United States Army, 1968-1970; lawyer, private practice; North Carolina resident superior court judge, 1989-2001; North Carolina special superior court judge, 2002-2004; justice of the North Carolina state supreme court, 2001-2002; elected as a Democrat to the One Hundred Eighth Congress, by special election, to fill the vacancy caused by the resignation of United States Representative Frank Ballance, and reelected to the seven succeeding Congresses (July 20, 2004-present).", "name": {"last": "Butterfield", "first": "George", "middle": "Kenneth"}, "date_of_birth": {"month": "April", "day": "27", "year": "1947"}, "place_of_birth": "Wilson, Wilson County, N.C.", "post_secondary_degrees": [{"degree": "B.A.", "year": "1971", "institution": "North Carolina Central University, Durham, N.C."}, {"degree": "J.D.", "year": "1974", "institution": "North Carolina Central University School of Law"}]}