{"id": "B001303", "update_date": "2017-12-31", "biography_text": "BLUNT ROCHESTER, Lisa, a Representative from Delaware; born in Philadelphia, Philadelphia County, Pa., February 10, 1962; graduated from Padua Academy, Wilmington, Del., 1980; B.A., Fairleigh Dickinson University, Rutherford, N.J., 1985; M.A., University of Delaware, Newark, Del., 2003; staff, United States Representative Thomas Richard Carper of Delaware; deputy secretary, Delaware department of health and social services, 1993-1998; Delaware state secretary of labor, 1998-2001; personnel director, Delaware office of management and budget, 2001-2004; chief executive officer, Metropolitan Wilmington Urban League, 2004-2007; senior fellow, University of Massachusetts, Boston, Mass., 2012-2015; elected as a Democrat to the One Hundred Fifteenth Congress (January 3, 2017-present).", "name": {"last": "Blunt rochester", "first": "Lisa"}, "date_of_birth": {"month": "February", "day": "10", "year": "1962"}, "place_of_birth": "Philadelphia, Philadelphia County, Pa.", "post_secondary_degrees": [{"degree": "B.A.", "year": "1985", "institution": "Fairleigh Dickinson University, Rutherford, N.J."}, {"degree": "M.A.", "year": "2003", "institution": "University of Delaware, Newark, Del."}]}