{"id": "B001304", "update_date": "2018-02-20", "biography_text": "BROWN, Anthony Gregory, a Representative from Maryland; born in Huntington, Suffolk County, N.Y., November 21, 1961; graduated from Huntington High School, Huntington, N.Y., 1979; attended United States Military Academy, West Point, N.Y.; A.B., Harvard University, Cambridge, Mass., 1984; J.D., Harvard University, Cambridge, Mass.,1992; United States Army, 1984-1989; United States Army Reserve, 1989-2014; lawyer, private practice; member of the Maryland state general assembly, 1999-2007, majority whip, 2004-2007; lieutenant governor of Maryland, 2007-2015; unsuccessful candidate for Governor of Maryland in 2014; elected as a Democrat to the One Hundred Fifteenth Congress (January 3, 2017-present).", "name": {"last": "Brown", "first": "Anthony", "middle": "Gregory"}, "date_of_birth": {"month": 11, "day": 21, "year": 1961}, "place_of_birth": "Huntington, Suffolk County, N.Y.", "post_secondary_degrees": [{"degree": "A.B.", "year": 1984, "institution": "Harvard University, Cambridge, Mass."}, {"degree": "J.D.", "year": 1992, "institution": "Harvard University, Cambridge"}]}