{"id": "B001236", "update_date": "2017-12-31", "biography_text": "BOOZMAN, John, a Senator and a Representative from Arkansas; born in Shreveport, La., December 10, 1950; graduated from Northside High School, Fort Smith, Ark.; attended the University of Arkansas, Fayetteville, Ark., 1969-1972; graduated Southern College of Optometry, 1977; optometrist; business owner; rancher; member of the Rogers, Ark., school board; elected as a Republican to the One Hundred Seventh Congress by special election to fill the vacancy caused by the resignation of United States Representative Asa Hutchinson; reelected to the four succeeding Congresses (November 20, 2001-January 3, 2011); was not a candidate for reelection to the House of Representatives but was elected as a Republican to the United States Senate in 2010; reelected in 2016  for the term ending January 3, 2023.", "name": {"last": "Boozman", "first": "John"}, "date_of_birth": {"month": "December", "day": "10", "year": "1950"}, "place_of_birth": "Shreveport, La."}