{"id": "B001267", "update_date": "2018-01-10", "biography_text": "BENNET, Michael F., a Senator from Colorado; born in New Delhi, India, November 28, 1964; B.A., Wesleyan University, Middletown, Conn., 1987; J.D., Yale Law School, 1993, editor-in-chief of the Yale Law Journal; counsel to U.S. deputy attorney general 1995-1997; special assistant U.S. attorney, Conn., 1997; managing director, Anschutz Investment Co. 1997-2003; chief of staff to mayor of Denver, Colo., 2003-2005; superintendent, Denver Public Schools 2005-2009; appointed January 21, 2009, to the United States Senate for the term ending January 3, 2011, to fill the vacancy caused by the resignation of Kenneth L. Salazar; took the oath of office on January 22, 2009; elected as a Democrat  to the U.S. Senate in 2010; reelected in 2016 for the term ending January 3, 2023; chair, Democratic Senatorial Campaign Committee (2013-2014).", "name": {"last": "Bennet", "first": "Michael", "middle": "F."}, "date_of_birth": {"month": 11, "day": 28, "year": 1964}, "place_of_birth": "New Delhi, India", "post_secondary_degrees": [{"degree": "B.A.", "year": 1987, "institution": "Wesleyan University, Middletown, Conn."}, {"degree": "J.D.", "year": 1993, "institution": "Yale Law School, editor-in-chief of the Yale Law Journal"}]}