{"id": "B001298", "update_date": "2018-02-20", "biography_text": "BACON, Donald J., a Representative from Nebraska; born in Chicago Heights, Cook County, Ill., August 16, 1963; graduated from Grace Baptist High School, Kankakee, Ill.; B.A., Northern Illinois University, DeKalb, Ill., 1984; M.B.A., University of Phoenix, Phoenix, Ariz., 1996; M.A., National War College, Washington, D.C., 2004; United States Air Force, 1985-2014; staff, United States Representative Jeff Fortenberry of Nebraska, 2014-2015; assistant professor, University of Bellevue, Bellevue, Nebr., 2014-2017; elected as a Republican to the One Hundred Fifteenth Congress (January 3, 2017-present).", "name": {"last": "Bacon", "first": "Donald", "middle": "J."}, "date_of_birth": {"month": 8, "day": 16, "year": 1963}, "place_of_birth": "Chicago Heights, Cook County, Ill.", "post_secondary_degrees": [{"degree": "B.A.", "year": 1984, "institution": "Northern Illinois University, DeKalb, Ill."}, {"degree": "M.B.A.", "year": 1996, "institution": "University of Phoenix, Phoenix, Ariz."}, {"degree": "M.A.", "year": 2004, "institution": "National War College, Washington, D.C."}]}