{"id": "C000984", "update_date": "2018-01-10", "biography_text": "CUMMINGS, Elijah Eugene, a Representative from Maryland; born in Baltimore, Md., January 18, 1951; graduated from Baltimore City College High School, Baltimore, Md., 1969; B.S., Howard University, Washington, D.C., 1973; J.D., University of Maryland School of Law, Baltimore, Md., 1976; lawyer, private practice; chief judge, Maryland Moot Court Board; member of the Maryland state house of delegates, 1983-1996, and speaker pro tempore, 1995-1996; elected as a Democrat to the One Hundred Fourth Congress, by special election, to fill the vacancy caused by the resignation of United States Representative Kweisi Mfume, and reelected to the eleven succeeding Congresses (April 16, 1996-present). ", "name": {"last": "Cummings", "first": "Elijah", "middle": "Eugene"}, "date_of_birth": {"month": "January", "day": "18", "year": "1951"}, "place_of_birth": "Baltimore, Md.", "post_secondary_degrees": [{"degree": "B.S.", "year": "1973", "institution": "Howard University, Washington, D.C."}, {"degree": "J.D.", "year": "1976", "institution": "University of Maryland School of Law, Baltimore, Md."}]}