{"id": "C001108", "update_date": "2018-02-20", "biography_text": "COMER, James, a Representative from Kentucky; born in Carthage, Smith County, Tenn., August 19, 1972; graduated from Monroe County High School, Tompkinsville, Ky.; B.S., Western Kentucky University, Bowling Green, Ky., 1993; businessman; farmer; chairman, Monroe County, Ky., Republican party, 1993-1995; Delegate, Republican National Convention, 1996; member of the Kentucky state house of representatives, 2001-2012; Kentucky state commissioner of agriculture, 2012-2015; elected simultaneously as a Republican to the One Hundred Fourteenth and to the One Hundred Fifteenth Congresses, by special election, to fill the vacancy caused by the resignation of United States Representative Ed Whitfield (November 8, 2016-present). ", "name": {"last": "Comer", "first": "James"}, "date_of_birth": {"month": 8, "day": 19, "year": 1972}, "place_of_birth": "Carthage, Smith County, Tenn.", "post_secondary_degrees": [{"degree": "B.S.", "year": 1993, "institution": "Western Kentucky University, Bowling Green, Ky."}]}