{"id": "C001105", "update_date": "2017-12-31", "biography_text": "COMSTOCK, Barbara J., a Representative from Virginia; born in Springfield, Hampden County, Mass., June 30, 1959; B.A., Middlebury College, Middlebury, Vt., 1981; J.D., Georgetown University, Washington, D.C., 1986; staff, United States Senator Edward Kennedy of Massachusetts; lawyer, private practice; staff, United States Representative Frank Wolf of Virginia, 1991-1995; staff, United States House of Representatives Committee on Oversight and Government Reform, 1995-1999; campaign aide; staff, United States Justice Department, 2002-2003; consultant; member of the Virginia state house of delegates, 2009-2014; elected as a Republican to the One Hundred Fourteenth and to the succeeding Congress (January 3, 2015-present).", "name": {"last": "Comstock", "first": "Barbara", "middle": "J."}, "date_of_birth": {"month": "June", "day": "30", "year": "1959"}, "place_of_birth": "Springfield, Hampden County, Mass.", "post_secondary_degrees": [{"degree": "B.A.", "year": "1981", "institution": "Middlebury College, Middlebury, Vt."}, {"degree": "J.D.", "year": "1986", "institution": "Georgetown University, Washington, D.C."}]}