{"id": "C001080", "update_date": "2018-01-10", "biography_text": "CHU, Judy, a Representative from California; born in Los Angeles, Los Angeles County, Calif., July 7, 1953; B.A., University of California, Los Angeles, Calif., 1974; Ph.D., California School of Professional Psychology, Los Angeles, Calif., 1979; professor, Los Angeles City College, Los Angeles, Calif., 1981-1988; professor, East Los Angeles College, Monterey Park, Calif., 1988-2001; member of the Garvey, Calif., school district, 1985-1988; member of the Monterey Park, Calif., city council, 1988-2001; Mayor of Monterey Park, Calif.; member of the California state assembly, 2001-2006; member of the California board of equalization, 2006-2009; vice chair of the California board of equalization, 2009; elected as a Democrat to the One Hundred Eleventh Congress, by special election, to fill the vacancy caused by the resignation of United States Representative Hilda Solis, and reelected to the four succeeding Congresses (July 14, 2009-present).", "name": {"last": "Chu", "first": "Judy"}, "date_of_birth": {"month": 7, "day": 7, "year": 1953}, "place_of_birth": "Los Angeles, Los Angeles County, Calif.", "post_secondary_degrees": [{"degree": "B.A.", "year": 1974, "institution": "University of California, Los Angeles, Calif."}, {"degree": "Ph.D.", "year": 1979, "institution": "California School of Professional Psychology, Los Angeles, Calif."}]}