{"id": "C001095", "update_date": "2018-12-23", "biography_text": "COTTON, Tom, a Senator and a Representative from Arkansas; born in Dardanelle, Yell County, Ark., May 13, 1977; A.B., Harvard University, Cambridge, Mass., 1998; attended Claremont Graduate University, Claremont, Calif., 1998-1999; J.D., Harvard University, Cambridge, Mass., 2002; United States Army, 2004-2009; clerk, U.S. Court of Appeals, 2002-2003; lawyer, private practice; management consultant; farmer; elected as a Republican to the One Hundred Thirteenth Congress (January 3, 2013-January 3, 2015); was not a candidate for reelection to the House of Representatives but was elected as a Republican to the United States Senate in 2014 for the term ending January 3, 2021.", "name": {"last": "Cotton", "first": "Tom"}, "date_of_birth": {"month": 5, "day": 13, "year": 1977}, "place_of_birth": "Dardanelle, Yell County, Ark.", "post_secondary_degrees": [{"degree": "A.B.", "year": 1998, "institution": "Harvard University, Cambridge, Mass."}, {"degree": "J.D.", "year": 2002, "institution": "Harvard University, Cambridge, Mass."}]}