{"id": "C001084", "update_date": "2018-02-20", "biography_text": "CICILLINE, David N., a Representative from Rhode Island; born in Providence, Providence County, R.I., July 15, 1961; graduated from Narragansett High School, Providence, R.I., 1979; B.A., Brown University, Providence, R.I., 1983; J.D., Georgetown University, Washington, D.C., 1986; public defender, Washington, D.C., 1986-1987; lawyer, private practice; lawyer, public advocate; faculty, Roger Williams Law School, Bristol, R.I.; unsuccessful nominee to the Rhode Island state senate in 1992; member of the Rhode Island state house of representatives, 1995-2003; Delegate, Democratic National Convention, 2008; Mayor of Providence R.I., 2003-2011; elected as a Democrat to the One Hundred Twelfth and to the three succeeding Congresses (January 3, 2011-present).", "name": {"last": "Cicilline", "first": "David", "middle": "N."}, "date_of_birth": {"month": 7, "day": 15, "year": 1961}, "place_of_birth": "Providence, Providence County, R.I.", "post_secondary_degrees": [{"degree": "B.A.", "year": 1983, "institution": "Brown University, Providence, R.I."}, {"degree": "J.D.", "year": 1986, "institution": "Georgetown University, Washington, D.C."}]}