{"id": "C001047", "update_date": "2018-01-10", "biography_text": "CAPITO, Shelley Moore,  (daughter of Arch Alfred Moore, Jr.), a Senator and a Representative from West Virginia; born in Glendale, Marshall County, W.Va., November 26, 1953; B.S., Duke University, Durham, N.C., 1975; M.Ed., University of Virginia, Charlottesville, Va., 1976; college counselor; member, West Virginia state house of representatives, 1997-2001; elected as a Republican to the One Hundred Seventh and to the six succeeding Congresses (January 3, 2001-January 3, 2015); was not a candidate for reelection to the House of Representatives but was elected as a Republican to the United States Senate in 2014 for the term ending January 3, 2021.", "name": {"last": "Capito", "first": "Shelley", "middle": "Moore"}, "date_of_birth": {"month": "November", "day": "26", "year": "1953"}, "place_of_birth": "Glendale, Marshall County, W.Va.", "post_secondary_degrees": [{"degree": "B.S.", "year": "1975", "institution": "Duke University, Durham, N.C."}, {"degree": "M.Ed.", "year": "1976", "institution": "University of Virginia, Charlottesville, Va."}]}