{"id": "C001111", "update_date": "2018-02-20", "biography_text": "CRIST, Charlie Joseph Jr., a Representative from Florida; born in Altoona, Blair County, Pa., July 24, 1956; graduated from St. Petersburg High School, St. Petersburg, Fla., 1974; attended Wake Forest University, Winston-Salem, N.C.; B.A., Florida State University, Tallahassee, Fla., 1978; J.D., Cumberland School of Law, Birmingham, Ala., 1981; lawyer, private practice; unsuccessful candidate for election to the Florida state senate in 1986; staff, United States Senator Connie Mack of Florida, 1989; member of the Florida state senate, 1993-1999; Florida deputy secretary of business and professional regulation, 1999-2001; Florida state education commissioner, 2001-2003; Florida state attorney general, 2003-2007; Governor of Florida, 2007-2011; unsuccessful candidate for election to the United States Senate in 2010; unsuccessful candidate for election for Governor of Florida in 2014; elected as a Democrat to the One Hundred Fifteenth Congress (January 3, 2017-present).", "name": {"last": "Crist", "first": "Charlie", "middle": "Joseph Jr."}, "date_of_birth": {"month": 7, "day": 24, "year": 1956}, "place_of_birth": "Altoona, Blair County, Pa.", "post_secondary_degrees": [{"degree": "B.A.", "year": 1978, "institution": "Florida State University, Tallahassee, Fla."}, {"degree": "J.D.", "year": 1981, "institution": "Cumberland School of Law, Birmingham, Ala."}]}