{"id": "C001072", "update_date": "2018-12-23", "biography_text": "CARSON, Andr\u00e9,  (grandson of Julia Carson),  a Representative from Indiana; born in Indianapolis, Marion County, Ind., October 16, 1974; graduated from Arsenal Technical High School, Indianapolis, Ind.; B.A., Concordia University Wisconsin, Mequon, Wis., 2003; M.S., Indiana Wesleyan University, Marion, Ind., 2005; marketing representative; state alcohol license compliance officer; member of the Indianapolis/Marion city-county council, 2007-2008; elected as a Democrat to the One Hundred Tenth Congress, by special election, to fill the vacancy caused by the death of United States Representative Julia Carson, and reelected to the five succeeding Congresses (March 11, 2008-present).", "name": {"last": "Carson", "first": "Andr\u00e9"}, "date_of_birth": {"month": 10, "day": 16, "year": 1974}, "place_of_birth": "Indianapolis, Marion County, Ind.", "post_secondary_degrees": [{"degree": "B.A.", "year": 2003, "institution": "Concordia University Wisconsin, Mequon, Wis."}, {"degree": "M.S.", "year": 2005, "institution": "Indiana Wesleyan University, Marion, Ind."}]}