{"id": "C001055", "update_date": "2019-01-04", "biography_text": "CASE, Ed, a Representative from Hawaii; born in Hilo, Territory of Hawaii, September 27, 1952; graduated from Hawaii Preparatory High School, Kamuela, Hawaii, 1970; B.A., Williams College, Williamstown, Mass., 1975; J.D., University of California, San Francisco, Calif., 1981; lawyer, private practice; business executive; staff, United States Representative Spark Matsunaga of Hawaii, 1975-1977; staff, United States Senator Spark Matsunaga of Hawaii, 1977-1978; member of the Hawaii state house of representatives, 1994-2002; unsuccessful candidate for nomination for Governor of Hawaii in 2002; elected as a Democrat to the One Hundred Seventh Congress, by special election, to fill the vacancy caused by the death of United States Representative Patsy Mink (November 30, 2002-January 3, 2003); elected as a Democrat to the One Hundred Eighth Congress, by special election, to fill the vacancy caused by the death of United States Representative Patsy Mink, and reelected to the succeeding Congress (January 4, 2003-January 3, 2007); was not a candidate for reelection to the One Hundred Tenth Congress in 2006, but was an unsuccessful candidate for nomination to the United States Senate; unsuccessful candidate for special election to the One Hundred Twelfth Congress in 2010; unsuccessful candidate for nomination to the United States Senate in 2012; elected as a Democrat to the One Hundred Sixteenth Congress (January 3, 2019-present). ", "name": {"last": "Case", "first": "Ed"}, "date_of_birth": {"month": 9, "day": 27, "year": 1952}, "place_of_birth": "Hilo, Territory of Hawaii", "post_secondary_degrees": [{"degree": "B.A.", "year": 1975, "institution": "Williams College, Williamstown, Mass."}, {"degree": "J.D.", "year": 1981, "institution": "University of California, San Francisco, Calif."}]}