{"id": "C001101", "update_date": "2019-01-04", "biography_text": "CLARK, Katherine M., a Representative from Massachusetts; born in New Haven, New Haven County, Conn., July 17, 1963; B.A., Saint Lawrence University, Canton, N.Y., 1985; J.D., Cornell University, Ithaca, N.Y., 1989; M.P.A., John F. Kennedy School of Government, Harvard University, Cambridge, Mass., 1997; lawyer, private practice; lawyer, Colorado district attorney's council; general counsel, Massachusetts state office of child care services; policy division chief, Office of the Attorney General, State of Massachusetts; clerk, federal court, 1990-1991; prosecutor, Office of the Attorney General, State of Colorado, 1991-1993; member of the Melrose, Mass. school committee, 2001-2007; member of the Massachusetts state house of representatives, 2008-2010; member of the Massachusetts state senate, 2010-2013; elected as a Democrat to the One Hundred Thirteenth Congress, by special election, to fill the vacancy caused by the resignation of United States Representative Edward J. Markey, and to the three succeeding Congresses (December 10, 2013-present). ", "name": {"last": "Clark", "first": "Katherine", "middle": "M."}, "date_of_birth": {"month": 7, "day": 17, "year": 1963}, "place_of_birth": "New Haven, New Haven County, Conn.", "post_secondary_degrees": [{"degree": "B.A.", "year": 1985, "institution": "Saint Lawrence University, Canton, N.Y."}, {"degree": "J.D.", "year": 1989, "institution": "Cornell University, Ithaca, N.Y."}, {"degree": "M.P.A.", "year": 1997, "institution": "John F. Kennedy School of Government, Harvard University, Cambridge, Mass."}]}