{"id": "C001114", "update_date": "2018-02-20", "biography_text": "CURTIS, John R., a Representative from Utah; born in Ogden, Weber County, Utah, May 10, 1960; graduated from Skyline High School, Salt Lake City, Utah, 1978; attended University of Utah, Salt Lake City, Utah, 1979; B.S., Brigham Young University, Provo, Utah, 1985; sales representative; business executive; unsuccessful candidate for Utah state senate in 2000; unsuccessful candidate for Utah state house of representatives in 2007; Mayor of Provo, Utah, 2009-2017; elected as a Republican to the One Hundred Fifteenth Congress, by special election, to fill the vacancy caused by the resignation of United States Representative Jason Chaffetz (November 7, 2017-present).", "name": {"last": "Curtis", "first": "John", "middle": "R."}, "date_of_birth": {"month": 5, "day": 10, "year": 1960}, "place_of_birth": "Ogden, Weber County, Utah", "post_secondary_degrees": [{"degree": "B.S.", "year": 1985, "institution": "Brigham Young University, Provo, Utah"}]}