{"id": "C001088", "update_date": "2018-01-10", "biography_text": "COONS, Christopher A., a Senator from Delaware; born on September 9, 1963, in Greenwich, Conn.; B.A., Amherst College, 1985; J.D., Yale University Law School, 1992; M.A.R., Yale Divinity School, 1992; worked in the non-profit sector; attorney; served as president of the New Castle County Council 2001-2005; County Executive of New Castle County 2005-2010; elected as a Democrat to the United States Senate in the November 2, 2010, special election to the term ending January 3, 2015, a seat previously held by appointed Senator Edward E. Kaufman, and took the oath of office on November 15, 2010; reelected in 2014 for the term ending January 3, 2021.", "name": {"last": "Coons", "first": "Christopher", "middle": "A."}, "date_of_birth": {"month": "September", "day": "9", "year": "1963"}, "place_of_birth": "", "post_secondary_degrees": [{"degree": "B.A.", "year": "1985", "institution": "Amherst College"}, {"degree": "J.D.", "year": "1992", "institution": "Yale University Law School"}, {"degree": "M.A.", "year": "1992", "institution": "Yale Divinity School"}]}