{"id": "C001063", "update_date": "2018-12-23", "biography_text": "CUELLAR, Henry, a Representative from Texas; born in Laredo, Webb County, Tex., September 19, 1955; graduated from J.W. Nixon High School, Laredo, Tex., 1974; A.A., Laredo Community College, Laredo, Tex., 1976; B.S., Georgetown University, Washington, D.C., 1978; J.D., University of Texas, Austin, Tex., 1981; M.A., Texas A&M International University, Laredo, Tex., 1982; Ph.D., University of Texas, Austin, Tex., 1998; lawyer, private practice; member of the Texas state house of representatives, 1987-2001; unsuccessful candidate for nomination to the United States of Representatives in 2002; Texas secretary of state, 2001; elected as a Democrat to the One Hundred Ninth and to the six succeeding Congresses (January 3, 2005-present).", "name": {"last": "Cuellar", "first": "Henry"}, "date_of_birth": {"month": 9, "day": 19, "year": 1955}, "place_of_birth": "Laredo, Webb County, Tex.", "post_secondary_degrees": [{"degree": "B.S.", "year": 1978, "institution": "Georgetown University, Washington, D.C."}, {"degree": "J.D.", "year": 1981, "institution": "University of Texas, Austin, Tex."}, {"degree": "M.A.", "year": 1982, "institution": "Texas A&M International University, Laredo, Tex."}, {"degree": "Ph.D.", "year": 1998, "institution": "University of Texas, Austin, Tex."}]}