{"id": "C001037", "update_date": "2017-12-31", "biography_text": "CAPUANO, Michael Everett, a Representative from Massachusetts; born in Somerville, Middlesex County, Mass., January 9, 1952; graduated from Somerville High School, Somerville, Mass., 1969; A.B., Dartmouth College, Hanover, N.H., 1973; J.D., Boston College, Chestnut Hill, Mass., 1977; lawyer, private practice; chief legal counsel, joint committee on taxation, Massachusetts state legislature, 1978-1984; alderman, Somerville, Mass., 1977-1979; alderman-at-large, Somerville, Mass., 1985-1989; Mayor of Somerville, Mass., 1990-1998; Democratic state committeeman, 1996; president, Massachusetts Municipal Association, 1998; elected as a Democrat to the One Hundred Sixth and to the nine succeeding Congresses (January 3, 1999-present).", "name": {"last": "Capuano", "first": "Michael", "middle": "Everett"}, "date_of_birth": {"month": "January", "day": "9", "year": "1952"}, "place_of_birth": "Somerville, Middlesex County, Mass.", "post_secondary_degrees": [{"degree": "A.B.", "year": "1973", "institution": "Dartmouth College, Hanover, N.H."}, {"degree": "J.D.", "year": "1977", "institution": "Boston College, Chestnut Hill, Mass."}]}