{"id": "D000629", "update_date": "2019-01-04", "biography_text": "DAVIDS, Sharice, a Representative from Kansas; born in Shawnee, Shawnee County, Kans., on May 22, 1980; a registered member of the Ho-Chunk Nation; graduated from Leavenworth High School, Leavenworth, Kans., 1998; attended Haskell Indian Nations University, Lawrence, Kans.; attended University of Kansas, Lawrence, Kans.; A.A., Johnson County Community College, Overland Park, Kans., 2003; B.A., University of Missouri, Kansas City, Mo., 2007; J.D., Cornell University, Ithaca, N.Y., 2010; teacher; lawyer; school administrator; business owner; non-profit executive; professional athlete; White House Fellow, 2016-2017; elected as a Democrat to the One Hundred Sixteenth Congress (January 3, 2019-present). ", "name": {"last": "Davids", "first": "Sharice"}, "date_of_birth": {"month": 5, "day": 22, "year": 1980}, "place_of_birth": "", "post_secondary_degrees": [{"degree": "B.A.", "year": 2007, "institution": "University of Missouri, Kansas City, Mo."}, {"degree": "J.D.", "year": 2010, "institution": "Cornell University, Ithaca, N.Y."}]}