{"id": "D000399", "update_date": "2017-12-31", "biography_text": "DOGGETT, Lloyd Alton, II, a Representative from Texas; born in Austin, Travis County, Tex., October 6, 1946; graduated from Austin High School, Austin, Tex., 1964; B.A., University of Texas, Austin, Tex., 1967; J.D., University of Texas School of Law, 1970; member of the Texas state senate, 1973-1985; justice of the Texas supreme court, 1989-1994; adjunct professor, University of Texas School of Law, Austin, Tex., 1989-1994; unsuccessful candidate for election to the United States Senate in 1984; elected as a Democrat to the One Hundred Fourth and to the eleven succeeding Congresses (January 3, 1995-present).", "name": {"last": "Doggett", "first": "Lloyd", "middle": "Alton"}, "date_of_birth": {"month": "October", "day": "6", "year": "1946"}, "place_of_birth": "Austin, Travis County, Tex.", "post_secondary_degrees": [{"degree": "B.A.", "year": "1967", "institution": "University of Texas, Austin, Tex."}, {"degree": "J.D.", "year": "1970", "institution": "University of Texas School of Law"}]}