{"id": "D000533", "update_date": "2018-02-20", "biography_text": "DUNCAN, John J., Jr.,  (son of John James Duncan), a Representative from Tennessee; born in Lebanon, Wilson County, Tenn., July 21, 1947; graduated from Holston High School, Knoxville, Tenn.; B.S., University of Tennessee, Knoxville, Tenn., 1969; J.D., National Law Center, George Washington University, Washington, D.C., 1973; lawyer, private practice; Army National Guard, 1970-1987; United States Army Reserve, 1970-1987; state trial judge, Knox County, Tenn., 1981-1988; elected as a Republican to the One Hundredth Congress, by special election, to fill the vacancy caused by the death of his father, John J. Duncan, and simultaneously elected to the One Hundred First Congress; reelected to the One Hundred Second and to the thirteen succeeding Congresses (November 8, 1988-present). ", "name": {"last": "Duncan", "first": "John", "middle": "J."}, "date_of_birth": {"month": 7, "day": 21, "year": 1947}, "place_of_birth": "Lebanon, Wilson County, Tenn.", "post_secondary_degrees": [{"degree": "B.S.", "year": 1969, "institution": "University of Tennessee, Knoxville, Tenn."}, {"degree": "J.D.", "year": 1973, "institution": "National Law Center, George Washington University, Washington, D.C."}]}