{"id": "D000617", "update_date": "2018-12-23", "biography_text": "DelBENE, Suzan K., a Representative from Washington; born in Selma, Dallas County, Ala., February 17, 1962; B.A., Reed College, Portland, Oreg. 1983; M.B.A., University of Washington, Seattle, Wash., 1990; business executive; unsuccessful candidate for election to the One Hundred Twelfth Congress  in 2010; director, Washington state department of revenue, 2010-2012; elected simultaneously as a Democrat to the One Hundred Twelfth and One Hundred Thirteenth Congresses, by special election, to fill the vacancy caused by the resignation of United States Representative Jay Inslee, and reelected to the two succeeding Congresses (November 6, 2012-present).", "name": {"last": "Delbene", "first": "Suzan", "middle": "K."}, "date_of_birth": {"month": 2, "day": 17, "year": 1962}, "place_of_birth": "Selma, Dallas County, Ala.", "post_secondary_degrees": [{"degree": "B.A.", "year": 1983, "institution": "Reed College, Portland"}, {"degree": "M.B.A.", "year": 1990, "institution": "University of Washington, Seattle, Wash."}]}