{"id": "D000624", "update_date": "2018-01-10", "biography_text": "DINGELL, Debbie,  (wife of John David Dingell, Jr.), a Representative from Michigan; born in Detroit, Wayne County, Mich., November 23, 1953; graduated from the Convent of the Sacred Heart, Grosse Pointe, Mich.; B.S.F.S., Georgetown University, Washington, D.C., 1975; M.S., Georgetown University, Washington, D.C., 1996; analyst; professional advocate; business executive; non-profit executive; board of governors, Wayne State University, 2007-2014; member of the Democratic National Committee; elected as a Democrat to the One Hundred Fourteenth and to the succeeding Congress (January 3, 2015-present).", "name": {"last": "Dingell", "first": "Debbie"}, "date_of_birth": {"month": "November", "day": "23", "year": "1953"}, "place_of_birth": "Detroit, Wayne County, Mich.", "post_secondary_degrees": [{"degree": "B.S.", "year": "1975", "institution": "Georgetown University, Washington, D.C."}, {"degree": "M.S.", "year": "1996", "institution": "Georgetown University, Washington, D.C."}]}