{"id": "D000216", "update_date": "2019-01-04", "biography_text": "DeLAURO, Rosa L., a Representative from Connecticut; born in New Haven, New Haven County, Conn., March 2, 1943; graduated from Lauralton Hall High School, Milford, Conn.; B.A., Marymount College, Tarrytown, N.Y., 1964; attended the London School of Economics, London, England, 1962-1963; M.A., Columbia University, New York, N.Y., 1966; staff, Mayor Frank Logue of New Haven, Conn., 1976-1977; campaign manager, Mayor Frank Logue, 1978; staff, New Haven, Conn., development administrator, 1977-1979; campaign manager for United States Senator Christopher J. Dodd of Connecticut, 1979-1980; staff, United States Senator Christopher J. Dodd of Connecticut, 1981-1987; executive director, Countdown \u201887, 1987-1988; executive director, EMILY\u2019S List, 1989-1990; elected as a Democrat to the One Hundred Second and to the fourteen succeeding Congresses (January 3, 1991-present). ", "name": {"last": "Delauro", "first": "Rosa", "middle": "L."}, "date_of_birth": {"month": 3, "day": 2, "year": 1943}, "place_of_birth": "New Haven, New Haven County, Conn.", "post_secondary_degrees": [{"degree": "B.A.", "year": 1964, "institution": "Marymount College, Tarrytown, N.Y."}, {"degree": "M.A.", "year": 1966, "institution": "Columbia University, New York, N.Y."}]}