{"id": "D000604", "update_date": "2018-12-23", "biography_text": "DENT, Charles W., a Representative from Pennsylvania; born in Allentown, Lehigh County, Pa., May 24, 1960; graduated from William Allen High School, Allentown, Pa., 1978; B.A., Pennsylvania State University, University Park, Pa., 1982; M.P.A., Lehigh University, Bethlehem, Pa., 1993; staff, United States Representative Donald Ritter of Pennsylvania; college administrator; sales representative; hotel clerk; member of the Pennsylvania state house of representatives, 1991-1998; member of the Pennsylvania state senate, 1999-2004; elected as a Republican to the One Hundred Ninth and to the six succeeding Congresses until his resignation on May 12, 2018 (January 3, 2005-May 12, 2018); chair, Committee on Ethics (One Hundred Fourteenth Congress).", "name": {"last": "Dent", "first": "Charles", "middle": "W."}, "date_of_birth": {"month": 5, "day": 24, "year": 1960}, "place_of_birth": "Allentown, Lehigh County, Pa.", "post_secondary_degrees": [{"degree": "B.A.", "year": 1982, "institution": "Pennsylvania State University, University Park, Pa."}, {"degree": "M.P.A.", "year": 1993, "institution": "Lehigh University, Bethlehem, Pa."}]}