{"id": "D000607", "update_date": "2018-01-10", "biography_text": "DONNELLY, Joe, a Senator and a Representative from Indiana; born in Queens, Queens County, N.Y., September 29, 1955; B.A., University of Notre Dame, Notre Dame, Ind., 1977; J.D., University of Notre Dame, Notre Dame, Ind., 1981; lawyer, private practice; business owner; unsuccessful candidate for the 108th Congress in 2004; elected as a Democrat to the One Hundred Tenth and to the two succeeding Congresses (January 3, 2007-January 3, 2013); was not a candidate for reelection to the House of Representatives but was elected as a Democrat to the United States Senate in 2012 for the term ending January 3, 2019.", "name": {"last": "Donnelly", "first": "Joe"}, "date_of_birth": {"month": "September", "day": "29", "year": "1955"}, "place_of_birth": "Queens, Queens County, N.Y.", "post_secondary_degrees": [{"degree": "B.A.", "year": "1977", "institution": "University of Notre Dame, Notre Dame, Ind."}, {"degree": "J.D.", "year": "1981", "institution": "University of Notre Dame, Notre Dame, Ind."}]}