{"id": "D000191", "update_date": "2017-12-31", "biography_text": "DeFAZIO, Peter Anthony, a Representative from Oregon; born in Needham, Norfolk County, Mass., May 27, 1947; graduated from Needham High School, Needham, Mass., 1965; B.A., Tufts University, Medford, Mass., 1969; M.A., University of Oregon, Eugene, Oreg., 1977; United States Air Force Reserve, 1967-1971; staff, United States Representative James Howard Weaver of Oregon, 1977-1982; member of the Lane County, Oreg., board of commissioners, 1983-1986, chair, 1985-1986; unsuccessful candidate for nomination to the United States Senate in a special primary election in 1995; elected as a Democrat to the One Hundredth and to the fifteen succeeding Congresses (January 3, 1987-present). ", "name": {"last": "Defazio", "first": "Peter", "middle": "Anthony"}, "date_of_birth": {"month": "May", "day": "27", "year": "1947"}, "place_of_birth": "Needham, Norfolk County, Mass.", "post_secondary_degrees": [{"degree": "B.A.", "year": "1969", "institution": "Tufts University, Medford, Mass."}, {"degree": "M.A.", "year": "1977", "institution": "University of Oregon, Eugene, Oreg."}]}