{"id": "D000631", "update_date": "2019-01-04", "biography_text": "DEAN, Madeleine, a Representative from Pennsylvania; born in Glenside, Montgomery County, Pa., June 6, 1959; graduated from Abington High School, Abington, Pa., 1977; attended Montgomery County College, Blue Bell, Pa.; attended Fels Institute of Government, University of Pennsylvania, Philadelphia, Pa.; B.A., La Salle University, Philadelphia, Pa., 1981; J.D., Widener University Delaware Law School, Chester, Pa., 1984; lawyer, private practice; faculty, La Salle University, Philadelphia, Pa., 2001-2012; columnist; member of the Pennsylvania state house of representatives, 2012-2018; elected as a Democrat to the One Hundred Sixteenth Congress (January 3, 2019-present).", "name": {"last": "Dean", "first": "Madeleine"}, "date_of_birth": {"month": 6, "day": 6, "year": 1959}, "place_of_birth": "Glenside, Montgomery County, Pa.", "post_secondary_degrees": [{"degree": "B.A.", "year": 1981, "institution": "La Salle University, Philadelphia, Pa."}, {"degree": "J.D.", "year": 1984, "institution": "Widener University Delaware Law School, Chester, Pa."}]}