{"id": "D000096", "update_date": "2018-01-10", "biography_text": "DAVIS, Danny K., a Representative from Illinois; born in Parkdale, Ashley County, Ark., September 6, 1941; graduated from Savage High School, Parkdale, Ark., 1957; B.A., Arkansas A.M.&N. College, Pine Bluff, Ark., 1961; M.S., Chicago State University, Chicago, Ill., 1968; Ph.D., Union Institute, Cincinnati, Ohio, 1977; clerk, Chicago, Ill., Post Office, 1961-1965; teacher, Chicago, Ill., public schools, 1962-1968; executive director, Greater Lawndale Conservation Commission, 1969; director of training, Martin L. King Neighborhood Health Center, 1969-1971; executive director, Westside Health Center, 1975-1981; alderman, Chicago, Ill., city council, 1979-1990; commissioner, Cook County, Ill., board, 1990-1996; college professor; unsuccessful candidate for election to the United States House of Representatives in 1984 and 1986; elected as a Democrat to the One Hundred Fifth and to the ten succeeding Congresses (January 3, 1997-present).", "name": {"last": "Davis", "first": "Danny", "middle": "K."}, "date_of_birth": {"month": 9, "day": 6, "year": 1941}, "place_of_birth": "Parkdale, Ashley County, Ark.", "post_secondary_degrees": [{"degree": "B.A.", "year": 1961, "institution": "Arkansas A.M.&N. College, Pine Bluff, Ark."}, {"degree": "M.S.", "year": 1968, "institution": "Chicago State University, Chicago, Ill."}, {"degree": "Ph.D.", "year": 1977, "institution": "Union Institute, Cincinnati, Ohio"}]}