{"id": "E000285", "update_date": "2018-01-10", "biography_text": "ENZI, Michael B., a Senator from Wyoming; born in Bremerton, Wash., February 1, 1944; attended public schools of Thermopolis and Sheridan, Wyo.; graduated, Sheridan High School 1962; received degree in accounting, George Washington University 1966; M.B.A. in retail marketing from Denver University 1968; served in Wyoming National Guard 1967-73; owned and operated family shoe stores in Gillette and Sheridan, Wyo., and Miles City, Mont.; accountant; Certified Professional in Human Resources, 1993-present; Mayor of Gillette 1975-1982; member, Wyoming house of representatives 1987-1991; member, Wyoming state senate 1991-1996; commissioner, Western Interstate Commission for Higher Education 1995-1996; elected as a Republican to the United States Senate in 1996; reelected in 2002, 2008, and again in 2014 for the term ending January 3, 2021; chair, Committee on Health, Education, Labor, and Pensions (One Hundred Ninth Congress), Committee on Budget (One Hundred Fourteenth and One Hundred Fifteenth Congresses). ", "name": {"last": "Enzi", "first": "Michael", "middle": "B."}, "date_of_birth": {"month": 2, "day": 1, "year": 1944}, "place_of_birth": "Bremerton, Wash.", "post_secondary_degrees": [{"degree": "M.B.A.", "year": 1968, "institution": ""}]}