{"id": "E000296", "update_date": "2018-02-20", "biography_text": "EVANS, Dwight, a Representative from Pennsylvania; born in Philadelphia, Philadelphia County, Pa., May 16, 1954; graduated from Germantown High School, Philadelphia, Pa., 1971; A.A., Community College of Philadelphia, Philadelphia, Pa.,1973; B.A., La Salle University, Philadelphia, Pa., 1975; teacher, Philadelphia, Pa., public schools; employment counselor, Urban League of Philadelphia, Pa.; member of the Pennsylvania state house of representatives, 1980-2016; unsuccessful candidate for nomination as lieutenant governor of Pennsylvania in 1986; unsuccessful candidate for nomination for Governor of Pennsylvania in 1994; unsuccessful candidate for nomination as Mayor of Philadelphia, Pa., in 1999 & 2007; elected simultaneously as a Democrat to the One Hundred Fourteenth and the One Hundred Fifteenth Congresses, by special election, to fill the vacancy caused by the resignation of United States Representative Chaka Fattah (November 8, 2016-present).", "name": {"last": "Evans", "first": "Dwight"}, "date_of_birth": {"month": 5, "day": 16, "year": 1954}, "place_of_birth": "Philadelphia, Philadelphia County, Pa.", "post_secondary_degrees": [{"degree": "B.A.", "year": 1975, "institution": "La Salle University, Philadelphia, Pa."}]}