{"id": "E000215", "update_date": "2017-12-31", "biography_text": "ESHOO, Anna Georges, a Representative from California; born in New Britain, Hartford County, Conn., December 13, 1942; A.A., Canada College, Redwood City, Calif., 1975; Democratic National Committeewoman from California, 1980-1992; chief of staff, speaker pro tempore of the California state assembly, 1981-1982; member of the San Mateo County, Calif., board of supervisors, 1983-1992, president, 1986; member, California Democratic state central executive committee; member of the Democratic National Commission on Presidential Nominations, 1982; unsuccessful candidate for election to the United States House of Representatives in 1988; elected as a Democrat to the One Hundred Third and to the twelve succeeding Congresses (January 3, 1993-present). ", "name": {"last": "Eshoo", "first": "Anna", "middle": "Georges"}, "date_of_birth": {"month": "December", "day": "13", "year": "1942"}, "place_of_birth": "New Britain, Hartford County, Conn."}