{"id": "E000297", "update_date": "2019-01-04", "biography_text": "ESPAILLAT, Adriano J., a Representative from New York; born in Santiago, Dominican Republic, September 27, 1954; graduated from Bishop Dubois High School, New York City, N.Y., 1974; B.S., Queens College, New York City, N.Y., 1978; attended New York University, New York City, N.Y; attended Rutgers University, New Brunswick, N.J.; coordinator, New York City Criminal Justice Agency, 1980-1988; director, Washington Heights, N.Y., victim services community office, 1992-1994; director, Project Right Start, 1994-1996; member of the New York state assembly, 1996-2010; member of the New York state senate, 2010-2016; unsuccessful candidate for nomination to the One Hundred Thirteenth Congress in 2012 and the One Hundred Fourteenth Congress in 2014; elected as a Democrat to the One Hundred Fifteenth Congress and to the succeeding Congress (January 3, 2017-present). ", "name": {"last": "Espaillat", "first": "Adriano", "middle": "J."}, "date_of_birth": {"month": 9, "day": 27, "year": 1954}, "place_of_birth": "Santiago, Dominican Republic", "post_secondary_degrees": [{"degree": "B.S.", "year": 1978, "institution": "Queens College, New York City, N.Y."}]}