{"id": "F000454", "update_date": "2017-12-31", "biography_text": "FOSTER, Bill, a Representative from Illinois; born in Madison, Wis., October 7, 1955; B.A. University of Wisconsin, Madison, Dane County, Wis., 1975; Ph.D., Harvard University, Cambridge, Mass., 1984; physicist; entrepreneur; board member, Batavia Foundation for Educational Excellence; elected as a Democrat to the One Hundred Tenth Congress, by special election, to fill the vacancy caused by the resignation of United States Representative John Dennis Hastert, and reelected to the succeeding Congress (March 8, 2008-January 3, 2011); unsuccessful candidate for reelection to the One Hundred Twelfth Congress in 2010; elected as a Democrat to the One Hundred Thirteenth and to the two succeeding Congresses (January 3, 2013-present).", "name": {"last": "Foster", "first": "Bill"}, "date_of_birth": {"month": "October", "day": "7", "year": "1955"}, "place_of_birth": "Madison, Wis.", "post_secondary_degrees": [{"degree": "B.A.", "year": "1975", "institution": "Madison, Dane County, Wis."}, {"degree": "Ph.D.", "year": "1984", "institution": "Harvard University, Cambridge, Mass."}]}