{"id": "F000469", "update_date": "2019-01-04", "biography_text": "FULCHER, Russell, a Representative from Idaho; born in Boise, Ada County, Idaho, on July 19, 1973; graduated from Meridian High School, Meridian, Idaho, 1980; B.S., Boise State University, Boise, Idaho, 1984; M.B.A., Boise State University, Boise, Idaho, 1988; businessman; realtor; member of the Idaho state senate, 2005-2014; unsuccessful candidate for nomination as Governor of Idaho in 2014; Delegate, Republican National Convention, 2016; unsuccessful candidate for nomination as Governor of Idaho in 2018; elected as a Republican to the One Hundred Sixteenth Congress (January 3, 2019-present). ", "name": {"last": "Fulcher", "first": "Russell"}, "date_of_birth": {"month": 7, "day": 19, "year": 1973}, "place_of_birth": "", "post_secondary_degrees": [{"degree": "B.S.", "year": 1984, "institution": "Boise State University, Boise, Idaho"}, {"degree": "M.B.A.", "year": 1988, "institution": "Boise State University, Boise, Idaho"}]}