{"id": "F000455", "update_date": "2018-12-23", "biography_text": "FUDGE, Marcia L., a Representative from Ohio; born in Cleveland, Cuyahoga County, Ohio, October 29, 1952; graduated from Shaker Heights High School, Shaker Heights, Ohio, 1971; B.S., Ohio State University, Columbus, Ohio, 1975; J.D., Cleveland Marshall College of Law, Cleveland State University, Cleveland, Ohio, 1983; lawyer, private practice; director, Cuyahoga County, Ohio, prosecutor\u2019s office; director, Cuyahoga County, Ohio, budget commission; director, Cuyahoga County, Ohio, personal property tax department; staff, United States Representative Stephanie Tubbs Jones of Ohio, 1999-2000; mayor of Warrensville Heights, Ohio, 2000-2008; elected as a Democrat to the One Hundred Tenth Congress, by special election, to fill the vacancy caused by the death of United States Representative Stephanie Tubbs Jones, and reelected to the five succeeding Congresses (November 18, 2008-present).", "name": {"last": "Fudge", "first": "Marcia", "middle": "L."}, "date_of_birth": {"month": 10, "day": 29, "year": 1952}, "place_of_birth": "Cleveland, Cuyahoga County, Ohio", "post_secondary_degrees": [{"degree": "B.S.", "year": 1975, "institution": "Ohio State University, Columbus, Ohio"}, {"degree": "J.D.", "year": 1983, "institution": "Cleveland Marshall College of Law, Cleveland State University, Cleveland, Ohio"}]}