{"id": "F000466", "update_date": "2018-02-20", "biography_text": "FITZPATRICK, Brian K.,  (brother of Michael G. Fitzpatrick), a Representative from Pennsylvania; born in Philadelphia, Philadelphia County, Pa., December 17, 1973; graduated from Bishop Egan High School, Fairless Hills, Pa., 1992; B.S.B.A., La Salle University, Philadelphia, Pa., 1996; M.B.A., Pennsylvania State University, University Park, Pa., 2001; J.D., Dickinson School of Law, Pennsylvania State University, Carlisle, Pa., 2001; judicial clerk, Eastern District of Pennsylvania, 2001-2002; special agent, Federal Bureau of Investigation; special assistant United States attorney for the Eastern District of Pennsylvania; lawyer, private practice; accountant; elected as a Republican to the One Hundred Fifteenth Congress (January 3, 2017-present).", "name": {"last": "Fitzpatrick", "first": "Brian", "middle": "K."}, "date_of_birth": {"month": 12, "day": 17, "year": 1973}, "place_of_birth": "Philadelphia, Philadelphia County, Pa.", "post_secondary_degrees": [{"degree": "B.S.", "year": 1996, "institution": "La Salle University, Philadelphia, Pa."}, {"degree": "M.B.A.", "year": 2001, "institution": "Pennsylvania State University, University Park, Pa."}, {"degree": "J.D.", "year": 2001, "institution": "Dickinson School of Law, Pennsylvania State University, Carlisle, Pa."}]}