{"id": "G000587", "update_date": "2019-01-04", "biography_text": "GARCIA, Sylvia, a Representative from Texas; born in Palito Blanco, Jim Wells County, Tex., September 6, 1950; graduated from Ben Bolt-Palito Blanco High School, Palito Blanco, Tex.; B.S.W., Texas Women's University, Denton, Tex., 1972; J.D., Texas Southern University, Houston, Tex., 1978; lawyer; social worker; director and presiding judge, Houston, Tex., municipal court system, 1983-1998; Houston, Tex., city controller, 1998-2003; member of the Harris County, Tex., commissioners court, 2003-2010; member of the Texas state senate, 2013-2019; unsuccessful candidate for nomination to the One Hundred Third Congress in 1992; elected as a Democrat to the One Hundred Sixteenth Congress (January 3, 2019-present). ", "name": {"last": "Garcia", "first": "Sylvia"}, "date_of_birth": {"month": 9, "day": 6, "year": 1950}, "place_of_birth": "Palito Blanco, Jim Wells County, Tex.", "post_secondary_degrees": [{"degree": "B.S.", "year": 1972, "institution": "Texas Women's University, Denton, Tex."}, {"degree": "J.D.", "year": 1978, "institution": "Texas Southern University, Houston, Tex."}]}