{"id": "G000566", "update_date": "2018-12-23", "biography_text": "GOWDY, Trey, a Representative from South Carolina; born in Greenville, Greenville County, S.C., August 22, 1964; graduated from Spartanburg High School, Spartanburg, S.C., 1982; B.A., Baylor University, Waco, Texas, 1986; J.D., University of South Carolina School of Law, Columbia, S.C., 1989; lawyer, private practice; clerk, South Carolina Court of Appeals; clerk, United States District Court; assistant U. S. attorney, district of South Carolina, 1994-2000; solicitor, Seventh Judicial Circuit, 2001-2010; elected as a Republican to the One Hundred Twelfth and to the three succeeding Congresses (January 3, 2011-present); chair, Select Committee on the Events Surrounding the 2012 Terrorist Attack in Benghazi (One Hundred Thirteenth Congress); chair, Committee on Oversight and Government Reform (One Hundred Fifteenth Congress).", "name": {"last": "Gowdy", "first": "Trey"}, "date_of_birth": {"month": 8, "day": 22, "year": 1964}, "place_of_birth": "Greenville, Greenville County, S.C.", "post_secondary_degrees": [{"degree": "B.A.", "year": 1986, "institution": "Baylor University, Waco, Texas"}, {"degree": "J.D.", "year": 1989, "institution": "University of South Carolina School of Law, Columbia, S.C."}]}