{"id": "G000583", "update_date": "2017-12-31", "biography_text": "GOTTHEIMER, Josh S., a Representative from New Jersey; born in North Caldwell, Essex County, N.J., March 8, 1975; graduated from West Essex Senior High School, North Caldwell, N.J., 1993; B.A., University of Pennsylvania, Philadelphia, Pa., 1997; J.D., Harvard Law School, Cambridge, Mass., 2004; special assistant and speechwriter for President William J. Clinton, 1998-2001; staff, Wesley Cark presidential campaign, 2004; staff, John Forbes Kerry presidential campaign, 2004; business executive; senior counselor to the chairman of the Federal Communications Commission, 2010-2012; elected as a Democrat to the One Hundred Fifteenth Congress (January 3, 2017-present).", "name": {"last": "Gottheimer", "first": "Josh", "middle": "S."}, "date_of_birth": {"month": "March", "day": "8", "year": "1975"}, "place_of_birth": "North Caldwell, Essex County, N.J.", "post_secondary_degrees": [{"degree": "B.A.", "year": "1997", "institution": "University of Pennsylvania, Philadelphia, Pa."}, {"degree": "J.D.", "year": "2004", "institution": "Harvard Law School, Cambridge, Mass."}]}