{"id": "G000579", "update_date": "2018-01-10", "biography_text": "GALLAGHER, Michael, a Representative from Wisconsin; born in Green Bay, Brown County, Wis., March 3, 1984; graduated from Mater Dei High School, Santa Ana, Calif., 2002; A.B., Princeton University, Princeton, N.J., 2006; M.S., National Intelligence University, Washington, D.C., 2010; M.A., Georgetown University, Washington, D.C., 2012; M.A., Georgetown University, Washington, D.C., 2013; Ph.D., Georgetown University, Washington, D.C., 2015; United States Marine Corps, 2006-2013; staff, United States Senate Foreign Relations Committee, 2013-2015; presidential campaign staff, Scott Walker, 2015; businessman; elected as a Republican to the One Hundred Fifteenth Congress (January 3, 2017-present).", "name": {"last": "Gallagher", "first": "Michael"}, "date_of_birth": {"month": 3, "day": 3, "year": 1984}, "place_of_birth": "Green Bay, Brown County, Wis.", "post_secondary_degrees": [{"degree": "A.B.", "year": 2006, "institution": "Princeton University, Princeton, N.J."}, {"degree": "M.S.", "year": 2010, "institution": "National Intelligence University, Washington, D.C."}, {"degree": "M.A.", "year": 2012, "institution": "Georgetown University, Washington, D.C."}, {"degree": "M.A.", "year": 2013, "institution": "Georgetown University, Washington, D.C."}, {"degree": "Ph.D.", "year": 2015, "institution": "Georgetown University, Washington, D.C."}]}