{"id": "G000592", "update_date": "2019-01-04", "biography_text": "GOLDEN, Jared, a Representative from Maine; born in Lewiston, Androscoggin County, Maine, July 25, 1982; graduated from Leavitt Area High School, Turner, Maine, 2001; attended University of Maine, Farmington, Maine, 2001-2002; B.A., Bates College, Lewiston, Maine, 2011; United States Marines Corps, 2002-2009; staff, United States Senate Committee on Homeland Security and Governmental Affairs, 2011-2012; staff, United States Senator Susan Collins of Maine, 2013; staff, Maine state house of representatives, 2013-2014; member of the Maine state house of representatives, 2014-2019; elected as a Democrat to the One Hundred Sixteenth Congress (January 3, 2019-present).", "name": {"last": "Golden", "first": "Jared"}, "date_of_birth": {"month": 7, "day": 25, "year": 1982}, "place_of_birth": "Lewiston, Androscoggin County, Maine", "post_secondary_degrees": [{"degree": "B.A.", "year": 2011, "institution": "Bates College, Lewiston, Maine"}]}