{"id": "G000582", "update_date": "2018-01-10", "biography_text": "GONZ\u00c1LEZ-C\u00d3LON, Jenniffer, a Resident Commissioner from Puerto Rico; born in San Juan, P.R., August 5, 1976; B.A., University of Puerto Rico, Rio Piedras, P.R.; J.D., Inter American University of Puerto Rico, San Juan, P.R.; L.L.M., Inter American University of Puerto Rico, San Juan, P.R.; chair, Puerto Rico Republican Party, 2015-present; co-chair, Puerto Rico Republican Party, 2004-2015; vice-president, New Progressive Party, 2008-present; member of the Puerto Rico house of representatives, 2002-2016; speaker, 2009-2012; minority leader, 2013-2016; elected as a New Progressive to the One Hundred Fifteenth Congress to a four-year term in 2017 (January 3, 2017-present).", "name": {"last": "Gonz\u00e1lez-c\u00f3lon", "first": "Jenniffer"}, "date_of_birth": {"month": 8, "day": 5, "year": 1976}, "place_of_birth": "San Juan, P.R.", "post_secondary_degrees": [{"degree": "B.A.", "institution": "University of Puerto Rico, Rio Piedras, P.R."}, {"degree": "J.D.", "institution": "Inter American University of Puerto Rico, San Juan, P.R."}]}