{"id": "H001036", "update_date": "2018-02-20", "biography_text": "HENSARLING, Jeb, a Representative from Texas; born in Stephenville, Erath County, Tex., May 29, 1957; B.A., Texas A&M University, College Station, Tex., 1979; J.D., University of Texas, Austin, Tex., 1982; lawyer, private practice; staff, United States Senator William Philip (Phil) Gramm of Texas, 1985-1989; business executive; elected as a Republican to the One Hundred Eighth and to the seven succeeding Congresses (January 3, 2003-present); chair, House Republican Conference (One Hundred Twelfth Congress); chair, Committee on Financial Services (One Hundred Thirteenth through One Hundred Fifteenth Congresses).", "name": {"last": "Hensarling", "first": "Jeb"}, "date_of_birth": {"month": 5, "day": 29, "year": 1957}, "place_of_birth": "Stephenville, Erath County, Tex.", "post_secondary_degrees": [{"degree": "B.A.", "year": 1979, "institution": "Texas A&M University, College Station, Tex."}, {"degree": "J.D.", "year": 1982, "institution": "University of Texas, Austin, Tex."}]}