{"id": "H001042", "update_date": "2018-12-23", "biography_text": "HIRONO, Mazie, a Senator and a Representative from Hawaii; born in Fukushima, Japan, November 3, 1947; graduated from Kaimuki High School, Honolulu, Hawaii; B.A., University of Hawaii, Manoa, Hawaii, 1970; J.D., Georgetown University, Washington, D.C., 1978; lawyer, private practice; member of the Hawaii state house of representatives, 1981-1994; Hawaii lieutenant governor, 1994-2002; elected as a Democrat to the One Hundred Tenth and to the two succeeding Congresses (January 3, 2007-January 3, 2013); was not a candidate for reelection to the House of Representatives but was elected as a Democrat to the United States Senate in 2012 for the term ending January 3, 2019.", "name": {"last": "Hirono", "first": "Mazie"}, "date_of_birth": {"month": 11, "day": 3, "year": 1947}, "place_of_birth": "Fukushima, Japan", "post_secondary_degrees": [{"degree": "B.A.", "year": 1970, "institution": "University of Hawaii, Manoa, Hawaii"}, {"degree": "J.D.", "year": 1978, "institution": "Georgetown University, Washington, D.C."}]}