{"id": "H001052", "update_date": "2017-12-31", "biography_text": "HARRIS, Andy,  a Representative from Maryland; born in Brooklyn, Kings County, N.Y., January 25, 1957; graduated from Regis High School, New York, N.Y., 1974; B.S., The Johns Hopkins University, Baltimore, Md., 1977; M.D., The Johns Hopkins University, Baltimore, Md., 1980; M.H.S., The Johns Hopkins University, Baltimore, Md., 1995; physician; United States Navy Reserve, 1988-2010; member of the Maryland state senate, 1998-2010, minority whip; unsuccessful candidate for election to the One Hundred Eleventh Congress in 2008; elected as a Republican to the One Hundred Twelfth and to the three succeeding Congresses (January 3, 2011-present).", "name": {"last": "Harris", "first": "Andy"}, "date_of_birth": {"month": "January", "day": "25", "year": "1957"}, "place_of_birth": "Brooklyn, Kings County, N.Y.", "post_secondary_degrees": [{"degree": "B.S.", "year": "1977", "institution": "The Johns Hopkins University, Baltimore, Md."}, {"degree": "M.D.", "year": "1980", "institution": "The Johns Hopkins University, Baltimore, Md."}]}