{"id": "H001075", "update_date": "2017-12-31", "biography_text": "HARRIS, Kamala Devi, a Senator from California; born in Oakland, Calif., October 20, 1964; B.A., Howard University, 1986; J.D., University of California, Hastings College of the Law, 1989; admitted to the California bar in 1990; deputy district attorney, Alameda County, Calif., 1990-1998; managing attorney, San Francisco District Attorney\u2019s Office; chief of the San Francisco City Attorney\u2019s Division on Children and Families; district attorney of San Francisco 2004-2011; attorney general of California 2011-2016; elected as a Democrat to the United States Senate in 2016 for the term ending January 3, 2023.", "name": {"last": "Harris", "first": "Kamala", "middle": "Devi"}, "date_of_birth": {"month": "October", "day": "20", "year": "1964"}, "place_of_birth": "Oakland, Calif.", "post_secondary_degrees": [{"degree": "B.A.", "year": "1986", "institution": "Howard University"}, {"degree": "J.D.", "year": "1989", "institution": "University of California, Hastings College of the Law"}]}