{"id": "H001050", "update_date": "2018-01-10", "biography_text": "HANABUSA, Colleen, a Representative from Hawaii; born in Honolulu, Honolulu County, Hawaii, May 4, 1951; graduated from St. Andrew\u0092s Priory School, Honolulu, Hawaii, 1969; B.A., University of Hawaii, Manoa, Hawaii, 1973; M.A., University of Hawaii, Manoa, Hawaii, 1975; J.D., University of Hawaii, Manoa, Hawaii, 1977; lawyer, private practice; member of the Hawaii state senate, 1998-2010, president, 2007-2010; unsuccessful candidate for nomination to the One Hundred Eighth Congress in a special election in 2003; unsuccessful candidate for nomination to the One Hundred Ninth Congress in 2006; unsuccessful candidate for election to the One Hundred Eleventh Congress in a special election in 2010; elected as a Democrat to the One Hundred Twelfth and to the succeeding Congress (January 3, 2011-January 3, 2015); was not a candidate for reelection to the One Hundred Fourteenth Congress in 2014, but was an unsuccessful candidate for nomination to the United States Senate; lawyer, private practice; elected simultaneously as a Democrat to the One Hundred Fourteenth and the One Hundred Fifteenth Congresses, by special election, to fill the vacancy caused by the death of United States Representative Mark Takai (November 8, 2016-present).", "name": {"last": "Hanabusa", "first": "Colleen"}, "date_of_birth": {"month": "May", "day": "4", "year": "1951"}, "place_of_birth": "Honolulu, Honolulu County, Hawaii", "post_secondary_degrees": [{"degree": "B.A.", "year": "1973", "institution": "University of Hawaii, Manoa, Hawaii"}, {"degree": "M.A.", "year": "1975", "institution": "University of Hawaii, Manoa, Hawaii"}, {"degree": "J.D.", "year": "1977", "institution": "University of Hawaii, Manoa, Hawaii"}]}