{"id": "H001080", "update_date": "2019-01-04", "biography_text": "HAALAND, Debra, a Representative from New Mexico; born in Winslow, Navajo County, Ariz., December 2, 1960; a registered member of the Laguna Pueblo; graduated from Highland High School, Albuquerque, N. Mex., 1978; B.A., University of New Mexico, Albuquerque, N.Mex., 1994; attended University of California, Los Angeles, Calif., 2000; J.D., University of New Mexico, Albuquerque, N. Mex., 2006; business executive; Delegate, Democratic National Convention, 2008; tribal administrator, San Felipe Pueblo, 2013-2015; chair, New Mexico Democratic Party, 2015-2017; elected as a Democrat to the One Hundred Sixteenth Congress (January 3, 2019-present).", "name": {"last": "Haaland", "first": "Debra"}, "date_of_birth": {"month": 12, "day": 2, "year": 1960}, "place_of_birth": "Winslow, Navajo County, Ariz.", "post_secondary_degrees": [{"degree": "B.A.", "year": 1994, "institution": "University of New Mexico, Albuquerque, N.Mex."}, {"degree": "J.D.", "year": 2006, "institution": "University of New Mexico, Albuquerque, N. Mex."}]}