{"id": "H001067", "update_date": "2018-01-10", "biography_text": "HUDSON, Richard, a Representative from North Carolina; born in Franklin, Va., November 4, 1971; graduated from Myers Park High School, Charlotte, N.C., 1990; B.A., University of North Carolina, Charlotte, N.C., 1996; communications director, North Carolina Republican party; business owner; staff, United States Representative Robert (Robin) Hayes of North Carolina, 2000-2005; staff, United States Representative Virginia Ann Foxx of North Carolina, 2005-2006; staff, United States Representative John R. Carter of Texas, 2006-2009; staff, United States Representative K. Michael Conaway of Texas, 2009-2011; elected as a Republican to the One Hundred Thirteenth and to the two succeeding Congresses (January 3, 2013-present).", "name": {"last": "Hudson", "first": "Richard"}, "date_of_birth": {"month": 11, "day": 4, "year": 1971}, "place_of_birth": "Franklin, Va.", "post_secondary_degrees": [{"degree": "B.A.", "year": 1996, "institution": "University of North Carolina, Charlotte, N.C."}]}