{"id": "H001072", "update_date": "2019-01-04", "biography_text": "HILL, French, a Representative from Arkansas; born in Little Rock, Pulaski County, Ark., December 5, 1956; graduated from Little Rock Catholic High School, Little Rock, Ark., 1975; B.S., Vanderbilt University, Nashville, Tenn., 1979; banker; businessman; staff, United States Senator John Tower and the United States Senate Committee on Banking, Housing, and Urban Affairs, 1982-1984; deputy assistant secretary, United States Treasury, 1989-1991; special assistant to President George H. W. Bush and Executive Secretary of Economic Policy Council, 1991-1993; senior advisor, Governor Mike Huckabee of Arkansas, 2008; elected as a Republican to the One Hundred Fourteenth Congress and to the two succeeding Congresses (January 3, 2015-present). ", "name": {"last": "Hill", "first": "French"}, "date_of_birth": {"month": 12, "day": 5, "year": 1956}, "place_of_birth": "Little Rock, Pulaski County, Ark.", "post_secondary_degrees": [{"degree": "B.S.", "year": 1979, "institution": "Vanderbilt University, Nashville, Tenn."}]}