{"id": "H001068", "update_date": "2018-01-10", "biography_text": "HUFFMAN, Jared, a Representative from California; born in Independence, Jackson County, Mo., February 18, 1964; graduated from William Chrisman High School, Independence, Mo., 1982; B.A., University of California, Santa Barbara, Calif., 1986; J.D., Boston College, Newton, Mass., 1990; lawyer, private practice; senior attorney, Natural Resources Defense Council, 2001-2006; member of the Marin County, Calif., municipal water district board of directors, 2001-2006; member of the California state assembly, 2006-2012; elected as a Democrat to the One Hundred Thirteenth and to the two succeeding Congresses (January 3, 2013-present).", "name": {"last": "Huffman", "first": "Jared"}, "date_of_birth": {"month": 2, "day": 18, "year": 1964}, "place_of_birth": "Independence, Jackson County, Mo.", "post_secondary_degrees": [{"degree": "B.A.", "year": 1986, "institution": "University of California, Santa Barbara, Calif."}, {"degree": "J.D.", "year": 1990, "institution": "Boston College, Newton, Mass."}]}