{"id": "J000174", "update_date": "2018-12-23", "biography_text": "JOHNSON, Sam, a Representative from Texas; born in San Antonio, Bexar County, Tex., October 11, 1930; graduated from Woodrow Wilson High School, Dallas, Tex.; B.B.A., Southern Methodist University, Dallas, Tex., 1951; M.S.I.A., George Washington University, Washington, D.C., 1974; United States Air Force, 1950-1979; prisoner of war during the Vietnam War, 1966-1973; decorated combat veteran, received two Silver Stars, two Legions of Merit, the Distinguished Flying Cross, one Bronze Star with Valor, two Purple Hearts, four Air Medals, and three outstanding unit awards; member of the Texas state house of representatives, 1985-1991; elected as a Republican to the One Hundred Second Congress, by special election, to fill the vacancy caused by the resignation of United States Representative Harry Stephen (Steve) Bartlett, and reelected to the One Hundred Third and to the twelve succeeding Congresses (May 8, 1991-present). ", "name": {"last": "Johnson", "first": "Sam"}, "date_of_birth": {"month": 10, "day": 11, "year": 1930}, "place_of_birth": "San Antonio, Bexar County, Tex.", "post_secondary_degrees": [{"degree": "M.S.", "year": 1974, "institution": "George Washington University, Washington, D.C."}]}