{"id": "J000297", "update_date": "2018-12-23", "biography_text": "JENKINS, Evan H., a Representative from West Virginia; born in Huntington, Cabell County, W.Va., September 12, 1960; B.S., University of Florida, Gainesville, Fla., 1983; J.D., Cumberland School of Law, Samford University, Birmingham, Ala., 1987; lawyer, private practice; businessman; instructor, Marshall University, Huntington, W.Va.; member of the West Virginia state house of delegates, 1994-1998; member of the West Virginia state senate, 2002-2014; elected as a Republican to the One Hundred Fourteenth and to the succeeding Congress until his resignation on September 30, 2018 (January 3, 2015-September 30, 2018); judge, W.Va., court of appeals, 2018-present.", "name": {"last": "Jenkins", "first": "Evan", "middle": "H."}, "date_of_birth": {"month": 9, "day": 12, "year": 1960}, "place_of_birth": "Huntington, Cabell County, W.Va.", "post_secondary_degrees": [{"degree": "B.S.", "year": 1983, "institution": "University of Florida, Gainesville, Fla."}, {"degree": "J.D.", "year": 1987, "institution": "Cumberland School of Law, Samford University, Birmingham, Ala."}]}