{"id": "J000300", "update_date": "2018-01-10", "biography_text": "JONES, Gordon Douglas (Doug), a Senator from Alabama; born in Fairfield, Ala., May 4, 1954; B.S., University of Alabama, 1976; J.D., Samford University, Cumberland School of Law, 1979; staff counsel to Alabama senator Howell Heflin on the U.S. Senate Committee on the Judiciary; assistant U.S. attorney for the Northern District of Alabama, 1980-1984; practiced law in Birmingham, Ala., U.S. attorney for the Northern District of Alabama, 1997-2001; elected as a Democrat to the United States Senate in a special election on December 12, 2017, to fill the vacancy caused by the resignation of Jefferson Sessions, a seat subsequently held by appointed senator Luther Strange, for the term ending January 3, 2021, and took the oath of office on January 3, 2018.", "name": {"last": "Jones", "first": "Gordon", "middle": "Douglas", "nickname": "Doug"}, "date_of_birth": {"month": 5, "day": 4, "year": 1954}, "place_of_birth": "Fairfield, Ala.", "post_secondary_degrees": [{"degree": "B.S.", "year": 1976, "institution": "University of Alabama"}, {"degree": "J.D.", "year": 1979, "institution": "Samford University, Cumberland School of Law"}]}