{"id": "J000288", "update_date": "2018-02-20", "biography_text": "JOHNSON, Hank, a Representative from Georgia; born in Washington, D.C., October 2, 1954; B.A., Clark College (Clark Atlanta University), Atlanta, Ga., 1976; J.D., Thurgood Marshall School of Law, Texas Southern University, Houston, Tex., 1979; lawyer, private practice; member of the DeKalb County, Ga., board of commissioners, 2001-2006; associate judge, DeKalb County, Ga., magistrate court, 1989-2001; one of the managers appointed by the House of Representatives in 2009 to conduct the impeachment proceedings of Samuel B. Kent, judge of the United States District Court for the Southern District of Texas; elected as a Democrat to the One Hundred Tenth and to the five succeeding Congresses (January 3, 2007-present).", "name": {"last": "Johnson", "first": "Hank"}, "date_of_birth": {"month": 10, "day": 2, "year": 1954}, "place_of_birth": "Washington, D.C.", "post_secondary_degrees": [{"degree": "B.A.", "year": 1976, "institution": "Clark College (Clark Atlanta University), Atlanta, Ga."}, {"degree": "J.D.", "year": 1979, "institution": "Thurgood Marshall School of Law, Texas Southern University, Houston, Tex."}]}