{"id": "J000294", "update_date": "2019-01-04", "biography_text": "JEFFRIES, Hakeem, a Representative from New York; born in Brooklyn, Kings County, N.Y., August 4, 1970; B.A., Binghamton University, Vestal, N.Y., 1992; M.P.P., Georgetown University, Washington, D.C., 1994; J.D., New York University, New York, N.Y., 1997; law clerk, United States District Court for the Southern District of New York, 1997-1998; lawyer, private practice; member of the New York state assembly, 2007-2012; elected as a Democrat to the One Hundred Thirteenth and to the three succeeding Congresses (January 3, 2013-present); chair, House Democratic Caucus (One Hundred Sixteenth Congress). ", "name": {"last": "Jeffries", "first": "Hakeem"}, "date_of_birth": {"month": 8, "day": 4, "year": 1970}, "place_of_birth": "Brooklyn, Kings County, N.Y.", "post_secondary_degrees": [{"degree": "B.A.", "year": 1992, "institution": "Binghamton University, Vestal, N.Y."}, {"degree": "J.D.", "year": 1997, "institution": "New York University, New York, N.Y."}]}