{"id": "K000388", "update_date": "2018-01-10", "biography_text": "KELLY, Trent, a Representative from Mississippi; born March 1, 1966, Union, Union County, Miss.; graduated from Union High School, Union, Miss., 1984; A.A., East Central Community College, Decatur, Miss., 1986; B.A., University of Mississippi, University, Miss., 1989; J.D., University of Mississippi, Oxford, Miss., 1994; M.A., United States Army War College, Carlisle, Penn., 2010; United States Army National Guard; lawyer, private practice; prosecutor, Tupelo, Miss., 1999-2011; district attorney, 2012-2015; elected as a Republican to the One Hundred Fourteenth Congress, by special election, to fill the vacancy caused by the death of United States Representative Alan Nunnelee, and reelected to the succeeding Congress (June 2, 2015-present). ", "name": {"last": "Kelly", "first": "Trent"}, "date_of_birth": {"month": 3, "day": 1, "year": 1966}, "place_of_birth": "", "post_secondary_degrees": [{"degree": "B.A.", "year": 1989, "institution": "University of Mississippi, University, Miss."}, {"degree": "J.D.", "year": 1994, "institution": "University of Mississippi, Oxford, Miss."}, {"degree": "M.A.", "year": 2010, "institution": "United States Army War College, Carlisle, Penn."}]}