{"id": "K000210", "update_date": "2018-01-10", "biography_text": "KING, Peter T., a Representative from New York; born in New York, New York County, N.Y., April 5, 1944; B.A., St. Francis College, Brooklyn Heights, N.Y., 1965; J.D., Notre Dame University, Notre Dame, Ind., 1968; New York Army National Guard, 1968-1973; lawyer, private practice; Nassau County, N.Y. deputy attorney, 1972-1974; member of the Hempstead, N.Y., town council, 1977-1981; Nassau County, N.Y. comptroller, 1981-1993; elected as a Republican to the One Hundred Third and to the twelve succeeding Congresses (January 3, 1993-present); chair, Committee on Homeland Security (One Hundred Ninth and One Hundred Twelfth Congresses).", "name": {"last": "King", "first": "Peter", "middle": "T."}, "date_of_birth": {"month": 4, "day": 5, "year": 1944}, "place_of_birth": "New York, New York County, N.Y.", "post_secondary_degrees": [{"degree": "B.A.", "year": 1965, "institution": "St. Francis College, Brooklyn Heights, N.Y."}, {"degree": "J.D.", "year": 1968, "institution": "Notre Dame University, Notre Dame, Ind."}]}