{"id": "K000379", "update_date": "2018-02-20", "biography_text": "KENNEDY, Joseph P. III,  (son of Joseph Patrick Kennedy, II, great-nephew of Edward Moore Kennedy and John Fitzgerald Kennedy, and great-great-grandson of John Francis Fitzgerald, first cousin once removed of Patrick Joseph Kennedy), a Representative from Massachusetts; born in Brighton, Suffolk County, Mass., October 4, 1980; B.S., Stanford University, Stanford, Calif., 2003; J.D., Harvard University, Cambridge, Mass., 2009; United States Peace Corps, 2004-2006; research analyst; Middlesex, Mass. county assistant district attorney, 2011-2012; elected as a Democrat to the One Hundred Thirteenth Congress and to the two succeeding Congresses (January 3, 2013-present).", "name": {"last": "Kennedy", "first": "Joseph", "middle": "P. III"}, "date_of_birth": {"month": 10, "day": 4, "year": 1980}, "place_of_birth": "Brighton, Suffolk County, Mass.", "post_secondary_degrees": [{"degree": "B.S.", "year": 2003, "institution": "Stanford University, Stanford, Calif."}, {"degree": "J.D.", "year": 2009, "institution": "Harvard University, Cambridge, Mass."}]}