{"id": "L000581", "update_date": "2018-01-10", "biography_text": "LAWRENCE, Brenda L., a Representative from Michigan; born in Detroit, Wayne County, Mich., October 18, 1954; graduated from Pershing High School, Detroit, Mich.; attended University of Detroit Mercy, Detroit, Mich.; B.A., Central Michigan University, Mt. Pleasant, Mich., 2005; manager, United States Postal Service; member of the Southfield, Mich., board of education, 1992-1996; member of the Southfield, Mich., city council, 1997-2001; Mayor of Southfield, Mich., 2001-2014; unsuccessful candidate for Oakland County, Mich., executive in 2008; unsuccessful candidate for Michigan lieutenant governor in 2010; elected as a Democrat to the One Hundred Fourteenth and to the succeeding Congress (January 3, 2015-present).", "name": {"last": "Lawrence", "first": "Brenda", "middle": "L."}, "date_of_birth": {"month": 10, "day": 18, "year": 1954}, "place_of_birth": "Detroit, Wayne County, Mich.", "post_secondary_degrees": [{"degree": "B.A.", "year": 2005, "institution": "Central Michigan University, Mt. Pleasant, Mich."}]}