{"id": "L000566", "update_date": "2018-01-10", "biography_text": "LATTA, Robert E.,  (son of Delbert L. Latta),  a Representative from Ohio; born in Bluffton, Allen County, Ohio, April 18, 1956; B.A., Bowling Green State University, Bowling Green, Ohio, 1978; J.D., University of Toledo, Toledo, Ohio, 1981; lawyer, private practice; Wood County, Ohio, commissioner, 1991-1996; member of the Ohio state senate, 1997-2000; member of the Ohio state house of representatives, 2001-2007; elected as a Republican to the One Hundred Tenth Congress, by special election, to fill the vacancy caused by the death of United States Representative Paul Eugene Gillmor, and reelected to the five succeeding Congresses (December 11, 2007-present).", "name": {"last": "Latta", "first": "Robert", "middle": "E."}, "date_of_birth": {"month": 4, "day": 18, "year": 1956}, "place_of_birth": "Bluffton, Allen County, Ohio", "post_secondary_degrees": [{"degree": "B.A.", "year": 1978, "institution": "Bowling Green State University, Bowling Green, Ohio"}, {"degree": "J.D.", "year": 1981, "institution": "University of Toledo, Toledo, Ohio"}]}