{"id": "L000582", "update_date": "2018-02-20", "biography_text": "LIEU, Ted, a Representative from California; born in Taipei, Taiwan, March 29, 1969; graduated from St. Ignatius High School, Cleveland, Ohio, 1987; B.A., Stanford University, Stanford, Calif., 1991; B.S., Stanford University, Stanford, Calif., 1991; J.D., Georgetown University, Washington, D.C., 1994; United States Air Force, 1995-1999; United States Air Force Reserve, 2000-present; judicial clerk, United States Court of Appeals, Ninth Circuit; lawyer, private practice; member of the Torrance, Calif., city council, 2002-2005; member of the California state assembly, 2005-2010; unsuccessful candidate for election for California state attorney general in 2010; member of the California state senate, 2011-2014; elected as a Democrat to the One Hundred Fourteenth and to the succeeding Congress (January 3, 2015-present).", "name": {"last": "Lieu", "first": "Ted"}, "date_of_birth": {"month": 3, "day": 29, "year": 1969}, "place_of_birth": "Taipei, Taiwan", "post_secondary_degrees": [{"degree": "B.A.", "year": 1991, "institution": "Stanford University, Stanford, Calif."}, {"degree": "B.S.", "year": 1991, "institution": "Stanford University, Stanford, Calif."}, {"degree": "J.D.", "year": 1994, "institution": "Georgetown University, Washington, D.C."}]}