{"id": "L000570", "update_date": "2019-01-04", "biography_text": "LUJ\u00c1N, Ben Ray, a Representative from New Mexico; born in Santa Fe, Santa Fe County, N.Mex., June 7, 1972; graduated from Pojoaque Valley High School, Santa Fe, N. Mex., 1990; attended University of New Mexico, Albuquerque, N.Mex., 1990-1995; B.B.A., New Mexico Highlands University, Las Vegas, N.Mex., 2007; member of the N.Mex. public regulation commission, 2004-2008; chairman, N.Mex. public regulation commission, 2005-2007; N.Mex. deputy state treasurer; director of administrative services, N.Mex. state cultural affairs department; chief financial officer, N.Mex. state cultural affairs department; elected as a Democrat to the One Hundred Eleventh and to the five succeeding Congresses (January 3, 2009-present); assistant Speaker (One Hundred Sixteenth Congress). ", "name": {"last": "Luj\u00e1n", "first": "Ben", "middle": "Ray"}, "date_of_birth": {"month": 6, "day": 7, "year": 1972}, "place_of_birth": "Santa Fe, Santa Fe County, N.Mex."}