{"id": "L000579", "update_date": "2018-01-10", "biography_text": "LOWENTHAL, Alan, a Representative from California; born in New York, New York County, N.Y., March 8, 1941; B.A., Hobart College, Geneva, N.Y., 1962; M.A., Ohio State University, Columbus, Ohio, 1965; Ph.D., Ohio State University, Columbus, Ohio, 1967; professor, California State University, Long Beach, Calif., 1969-1998; psychologist; member of the Long Beach, Calif., city council, 1992-1998; member of the California state assembly, 1998-2004; member of the California state senate, 2004-2012; elected as a Democrat to the One Hundred Thirteenth and to the two succeeding Congresses (January 3, 2013-present).", "name": {"last": "Lowenthal", "first": "Alan"}, "date_of_birth": {"month": 3, "day": 8, "year": 1941}, "place_of_birth": "New York, New York County, N.Y.", "post_secondary_degrees": [{"degree": "B.A.", "year": 1962, "institution": "Hobart College, Geneva, N.Y."}, {"degree": "M.A.", "year": 1965, "institution": "Ohio State University, Columbus, Ohio"}, {"degree": "Ph.D.", "year": 1967, "institution": "Ohio State University, Columbus, Ohio"}]}