{"id": "L000580", "update_date": "2018-12-23", "biography_text": "LUJAN GRISHAM, Michelle, a Representative from New Mexico; born in Los Alamos, Los Alamos County, N.Mex., October 24, 1959; graduated from St. Michael\u0092s High School, Santa Fe, N.Mex., 1977; B.S., University of New Mexico, Albuquerque, N.Mex., 1981; J.D., University of New Mexico, 1987; lawyer, New Mexico state bar association; business executive; director, New Mexico state agency on aging, 1991-2002; New Mexico secretary of aging and long-term services, 2002-2004; New Mexico secretary of health, 2004-2007; unsuccessful nominee for election to the One Hundred Eleventh Congress in 2008; Bernalillo County, N.Mex., board of commissioners, 2010-2012; elected as a Democrat to the One Hundred Thirteenth Congress and to the two succeeding Congresses (January 3, 2013-present).", "name": {"last": "Lujan grisham", "first": "Michelle"}, "date_of_birth": {"month": 10, "day": 24, "year": 1959}, "place_of_birth": "Los Alamos, Los Alamos County, N.Mex.", "post_secondary_degrees": [{"degree": "B.S.", "year": 1981, "institution": "University of New Mexico, Albuquerque, N.Mex."}, {"degree": "J.D.", "year": 1987, "institution": "University of New Mexico"}]}