{"id": "L000263", "update_date": "2018-02-20", "biography_text": "LEVIN, Sander Martin,  (brother of Carl Levin), a Representative from Michigan; born in Detroit, Wayne County, Mich., September 6, 1931; graduated from Central High School, Detroit, Mich.; B.A., University of Chicago, Chicago, Ill., 1952; M.A., Columbia University, New York, N.Y., 1954; LL.B., Harvard University, Cambridge, Mass., 1957; lawyer, private practice; member of the Michigan state senate, 1965-1970; unsuccessful candidate for Governor of Michigan in 1970 and 1974; assistant administrator, United States Agency for International Development, 1977-1981; delegate, Democratic National Conventions, 1964 and 1968; elected as a Democrat to the Ninety-eighth and to the seventeen succeeding Congresses (January 3, 1983-present); chairman, Committee on Ways and Means (One Hundred Eleventh Congress).", "name": {"last": "Levin", "first": "Sander", "middle": "Martin"}, "date_of_birth": {"month": 9, "day": 6, "year": 1931}, "place_of_birth": "Detroit, Wayne County, Mich.", "post_secondary_degrees": [{"degree": "B.A.", "year": 1952, "institution": "University of Chicago, Chicago, Ill."}, {"degree": "M.A.", "year": 1954, "institution": "Columbia University, New York, N.Y."}, {"degree": "LL.B.", "year": 1957, "institution": "Harvard University, Cambridge, Mass."}]}