{"id": "L000491", "update_date": "2018-12-23", "biography_text": "LUCAS, Frank D., a Representative from Oklahoma; born in Cheyenne, Roger Mills County, Okla., January 6, 1960; B.S., Oklahoma State University, Stillwater, Okla., 1982; chairman, Roger Mills County, Okla., Republican Party; staff, United States Senator Don Nickles of Oklahoma; member of the Oklahoma state house of representatives, 1988-1994; elected as a Republican to the One Hundred Third Congress, by special election, to fill the vacancy caused by the resignation of United States Representative Glenn English, and reelected to the twelve succeeding Congresses (May 10, 1994-present); chairman, Committee on Agriculture (One Hundred Twelfth and One Hundred Thirteenth Congresses).", "name": {"last": "Lucas", "first": "Frank", "middle": "D."}, "date_of_birth": {"month": 1, "day": 6, "year": 1960}, "place_of_birth": "Cheyenne, Roger Mills County, Okla.", "post_secondary_degrees": [{"degree": "B.S.", "year": 1982, "institution": "Oklahoma State University, Stillwater, Okla."}]}