{"id": "L000586", "update_date": "2019-01-04", "biography_text": "LAWSON, Alfred Jr., a Representative from Florida; born in Midway, Gadsden County, Fla., September 23, 1948; graduated from Havana Northside High School, Havana, Fla., 1966; B.S., Florida Agricultural and Mechanical University, Tallahassee, Fla., 1970; M.S.P.A., Florida State University, Tallahassee, Fla., 1973; business owner; member of the Florida state house of representatives, 1982-2000; member of the Florida state senate, 2000-2010; minority leader, 2008-2010; unsuccessful candidate for Democratic nomination to the One Hundred Twelfth Congress in 2010; unsuccessful candidate for election to the One Hundred Thirteenth Congress in 2012; elected as a Democrat to the One Hundred Fifteenth Congress and to the succeeding Congress (January 3, 2017-present). ", "name": {"last": "Lawson", "first": "Alfred", "middle": "Jr."}, "date_of_birth": {"month": 9, "day": 23, "year": 1948}, "place_of_birth": "Midway, Gadsden County, Fla.", "post_secondary_degrees": [{"degree": "B.S.", "year": 1970, "institution": "Florida Agricultural and Mechanical University, Tallahassee, Fla."}, {"degree": "M.S.", "year": 1973, "institution": "Florida State University, Tallahassee, Fla."}]}