{"id": "L000562", "update_date": "2018-12-23", "biography_text": "LYNCH, Stephen F., a Representative from Massachusetts; born in Boston, Suffolk County, Mass., March 31, 1955; graduated from South Boston High School, Boston, Mass., 1973; B.S., Wentworth Institute, Boston, Mass., 1988; J.D., Boston College, Chestnut Hill, Mass., 1991; M.A., Harvard University, Cambridge, Mass., 1998; member of the Massachusetts state house of representatives, 1995-1996; member of the Massachusetts state senate, 1997-2001; elected as a Democrat to the One Hundred Seventh Congress, by special election, to fill the vacancy caused by the death of United States Representative Joseph Moakley, and reelected to the eight succeeding Congresses (October 16, 2001-present).", "name": {"last": "Lynch", "first": "Stephen", "middle": "F."}, "date_of_birth": {"month": 3, "day": 31, "year": 1955}, "place_of_birth": "Boston, Suffolk County, Mass.", "post_secondary_degrees": [{"degree": "B.S.", "year": 1988, "institution": "Wentworth Institute, Boston, Mass."}, {"degree": "J.D.", "year": 1991, "institution": "Boston College, Chestnut Hill, Mass."}, {"degree": "M.A.", "year": 1998, "institution": "Harvard University, Cambridge, Mass."}]}