{"id": "L000287", "update_date": "2019-01-04", "biography_text": "LEWIS, John R., a Representative from Georgia; born in Troy, Pike County, Ala., February 21, 1940; attended Pike County Training School, Brundidge, Ala.; B.A., American Baptist Theological Seminary, Nashville, Tenn., 1961; B.A., Fisk University, Nashville, Tenn., 1967; chairman, Student Nonviolent Coordinating Committee, 1963-1966; director of ACTION, 1977-1980; community affairs director, National Consumer Co-op Bank, Atlanta, 1980-1986; member of the Atlanta, Ga., city council, 1982-1986; elected as a Democrat to the One Hundredth and to the sixteen succeeding Congresses (January 3, 1987-present). ", "name": {"last": "Lewis", "first": "John", "middle": "R."}, "date_of_birth": {"month": 2, "day": 21, "year": 1940}, "place_of_birth": "Troy, Pike County, Ala.", "post_secondary_degrees": [{"degree": "B.A.", "year": 1961, "institution": "American Baptist Theological Seminary, Nashville, Tenn."}, {"degree": "B.A.", "year": 1967, "institution": "Fisk University, Nashville, Tenn."}]}