{"id": "M001179", "update_date": "2018-01-10", "biography_text": "MARINO, Thomas A., a Representative from Pennsylvania; born in Williamsport, Lycoming County, Pa., August 15, 1952; graduated from Williamsport Area High School, Williamsport, Pa., 1970; A.A., Williamsport Area Community College, Williamsport, Pa., 1983; B.A., Lycoming College, Williamsport, Pa., 1985; J.D., Dickinson School of Law, Carlisle, Pa., 1988; manufacturing manager; lawyer, private practice; Lycoming County, Pa., district attorney, 1992-2002; United States attorney for the Middle District of Pennsylvania, 1992-2002; elected as a Republican to the One Hundred Twelfth and to the three succeeding Congresses (January 3, 2011-present).", "name": {"last": "Marino", "first": "Thomas", "middle": "A."}, "date_of_birth": {"month": 8, "day": 15, "year": 1952}, "place_of_birth": "Williamsport, Lycoming County, Pa.", "post_secondary_degrees": [{"degree": "B.A.", "year": 1985, "institution": "Lycoming College, Williamsport, Pa."}, {"degree": "J.D.", "year": 1988, "institution": "Dickinson School of Law, Carlisle, Pa."}]}