{"id": "M001182", "update_date": "2018-02-20", "biography_text": "MULVANEY, Mick, a Representative from South Carolina; born in Alexandria, Va., July 21, 1967; graduated from Charlotte Catholic High School, Charlotte, N.C., 1985; B.S.F.S., Georgetown University, Washington, D.C., 1989; J.D., University of North Carolina, Chapel Hill, N.C., 1992; lawyer, private practice; real estate developer; member of the South Carolina state house of representatives, 2007-2009; member of the South Carolina state senate, 2009-2010; elected as a Republican to the One Hundred Twelfth and to the three succeeding Congresses (January 3, 2011-February 16, 2017); Director of Office of Management and Budget under President Donald J. Trump, 2017-present.", "name": {"last": "Mulvaney", "first": "Mick"}, "date_of_birth": {"month": 7, "day": 21, "year": 1967}, "place_of_birth": "Alexandria, Va.", "post_secondary_degrees": [{"degree": "B.S.", "year": 1989, "institution": "Georgetown University, Washington, D.C."}, {"degree": "J.D.", "year": 1992, "institution": "University of North Carolina, Chapel Hill, N.C."}]}