{"id": "M001165", "update_date": "2018-01-10", "biography_text": "MCCARTHY, Kevin, a Representative from California; born in Bakersfield, Kern County, Calif., January 26, 1965; attended Bakersfield College, Bakersfield. Calif., 1984-1985; B.S., California State University, Bakersfield, Calif., 1989; M.B.A., California State University, Bakersfield, Calif., 1994; staff, United States Representative William Thomas of California, 1987-2002; member of the California state assembly, 2002-2007, minority leader, 2004-2006; elected as a Republican to the One Hundred Tenth and to the five succeeding Congresses (January 3, 2007-present); majority whip (One Hundred Twelfth and One Hundred Thirteenth Congresses); majority leader (One Hundred Thirteenth through One Hundred Fifteenth Congresses).", "name": {"last": "Mccarthy", "first": "Kevin"}, "date_of_birth": {"month": "January", "day": "26", "year": "1965"}, "place_of_birth": "Bakersfield, Kern County, Calif.", "post_secondary_degrees": [{"degree": "B.S.", "year": "1989", "institution": "California State University, Bakersfield, Calif."}, {"degree": "M.B.A.", "year": "1994", "institution": "California State University, Bakersfield, Calif."}]}