{"id": "M001169", "update_date": "2018-01-10", "biography_text": "MURPHY, Christopher, a Senator and a Representative from Connecticut; born in White Plains, Westchester County, N.Y., August 3, 1973; B.A., Williams College, Williamstown, Mass., 1996; attended Exeter College, Oxford, England, 1994-1995; J.D., University of Connecticut, Hartford, Conn., 2002; lawyer, private practice; Southington, Conn., planning and zoning commission, 1997-1999; member of the Connecticut state house of representatives, 1999-2003; member of the Connecticut state senate, 2003-2006; elected as a Democrat to the One Hundred Tenth and to the two succeeding Congresses (January 3, 2007-January 3, 2013); was not a candidate for reelection to the House of Representatives but was elected as a Democrat to the United States Senate in 2012 for the term ending January 3, 2019.", "name": {"last": "Murphy", "first": "Christopher"}, "date_of_birth": {"month": "August", "day": "3", "year": "1973"}, "place_of_birth": "White Plains, Westchester County, N.Y.", "post_secondary_degrees": [{"degree": "B.A.", "year": "1996", "institution": "Williams College, Williamstown, Mass."}, {"degree": "J.D.", "year": "2002", "institution": "University of Connecticut, Hartford, Conn."}]}