{"id": "M001197", "update_date": "2019-01-04", "biography_text": "McSALLY, Martha, a Senator and a Representative from Arizona; born in Warwick, Kent County, R.I., March 22, 1966; B.S., United States Air Force Academy, Colorado Springs, Colo., 1988; M.P.P., John F. Kennedy School of Government, Harvard University, Cambridge, Mass., 1990; United States Air Force, 1988-2010; fighter pilot; professor; unsuccessful candidate for nomination for special election to the One Hundred Twelfth Congress in 2012; unsuccessful candidate for election to the One Hundred Thirteenth Congress in 2012; elected as a Republican to the One Hundred Fourteenth and to the succeeding Congress (January 3, 2015-January 3, 2019); was not a candidate for reelection to the One Hundred Sixteenth Congress in 2018, but was an unsuccessful candidate for election to the United States Senate; appointed as a Republican to the United States Senate on January 3, 2019, to fill the vacancy caused by the death of John Sidney McCain, III; a seat previously held by appointed senator Jon Kyl, to serve until a special election is held on November 3, 2020, for the remainder of the term ending January 3, 2023. ", "name": {"last": "Mcsally", "first": "Martha"}, "date_of_birth": {"month": 3, "day": 22, "year": 1966}, "place_of_birth": "Warwick, Kent County, R.I.", "post_secondary_degrees": [{"degree": "B.S.", "year": 1988, "institution": "United States Air Force Academy, Colorado Springs, Colo."}]}