{"id": "M001181", "update_date": "2018-01-10", "biography_text": "MEEHAN, Patrick, a Representative from Pennsylvania; born in Cheltenham, Montgomery County, Pa., October 20, 1955; graduated from Chestnut Hill Academy, Philadelphia, Pa., 1974; B.A., Bowdoin College, Brunswick, Maine, 1978; J.D., Temple University, Philadelphia, Pa., 1986; lawyer, private practice; United States Attorney for the Eastern District of Pennsylvania, 2001-2008; staff, United States Senator Arlen Specter, 1991-1994; Delaware County, Pa., district attorney, 1996-2001; elected as a Republican to the One Hundred Twelfth and to the three succeeding Congresses (January 3, 2011-present).", "name": {"last": "Meehan", "first": "Patrick"}, "date_of_birth": {"month": "October", "day": "20", "year": "1955"}, "place_of_birth": "Cheltenham, Montgomery County, Pa.", "post_secondary_degrees": [{"degree": "B.A.", "year": "1978", "institution": "Bowdoin College, Brunswick, Maine"}, {"degree": "J.D.", "year": "1986", "institution": "Temple University, Philadelphia, Pa."}]}