{"id": "M001200", "update_date": "2019-01-04", "biography_text": "McEACHIN, Aston Donald, a Representative from Virginia; born in Nuremberg, Germany, October 10, 1961; graduated from St. Christopher's School, Richmond, Va., 1979; B.S., American University, Washington, D.C., 1982, J.D., University of Virginia, Charlottesville, Va., 1986; M.Div., Samuel DeWitt Proctor School of Theology at Virginia Union University, Richmond, Va., 2008; lawyer, private practice; member of the Virginia state house of delegates, 1996-2002 and 2006-2008; member of the Virginia state senate, 2008-2016; elected as a Democrat to the One Hundred Fifteenth Congress and to the succeeding Congress (January 3, 2017-present). ", "name": {"last": "Mceachin", "first": "Aston", "middle": "Donald"}, "date_of_birth": {"month": 10, "day": 10, "year": 1961}, "place_of_birth": "Nuremberg, Germany", "post_secondary_degrees": [{"degree": "J.D.", "year": 1986, "institution": "American University, Washington, D.C., University of Virginia, Charlottesville, Va."}]}