{"id": "N000147", "update_date": "2018-01-10", "biography_text": "NORTON, Eleanor Holmes, a Delegate from the District of Columbia; born in Washington, D.C., June 13, 1937; graduated from Dunbar High School, Washington, D.C.; B.A., Antioch College of Antioch University, Yellow Springs, Ohio, 1960; M.A., Yale University, New Haven, Conn., 1963; LL.B., Yale University Law School, New Haven, Conn., 1964; lawyer, private practice; law clerk to Federal District Court Judge A. Leon Higginbotham, 3rd Circuit, 1964-1965; assistant legal director, American Civil Liberties Union, 1965-1970; adjunct assistant professor, New York University Law School, 1970-1971; staff, New York, N.Y. Mayor John Lindsay, 1971-1974; chair, New York City commission on human rights, 1970-1977; chair, United States Equal Employment Opportunity Commission, 1977-1981; senior fellow, Urban Institute, 1981-1982; professor, Georgetown University Law Center, 1982-1990; elected as a Democrat to the One Hundred Second and to the thirteen succeeding Congresses (January 3, 1991-present). ", "name": {"last": "Norton", "first": "Eleanor", "middle": "Holmes"}, "date_of_birth": {"month": "June", "day": "13", "year": "1937"}, "place_of_birth": "Washington, D.C.", "post_secondary_degrees": [{"degree": "B.A.", "year": "1960", "institution": "Antioch College of Antioch University, Yellow Springs, Ohio"}, {"degree": "M.A.", "year": "1963", "institution": "Yale University, New Haven, Conn."}, {"degree": "LL.B.", "year": "1964", "institution": "Yale University Law School, New Haven, Conn."}]}