{"id": "N000181", "update_date": "2018-01-10", "biography_text": "NUNES, Devin, a Representative from California; born in Tulare County, Calif., October 1, 1973; A.A., College of the Sequoias, Visalia, Calif.; B.S., California Polytechnic State University, San Luis Obispo, Calif., 1995; M.S., California Polytechnic State University, San Luis Obispo, Calif., 1996; farmer; businessman; director, United States Department of Agriculture Rural Development, 2001; elected as a Republican to the One Hundred Eighth and to the seven succeeding Congresses (January 3, 2003-present); chair, Permanent Select Committee on Intelligence (One Hundred Fourteenth through One Hundred Fifteenth Congresses).", "name": {"last": "Nunes", "first": "Devin"}, "date_of_birth": {"month": 10, "day": 1, "year": 1973}, "place_of_birth": "Tulare County, Calif.", "post_secondary_degrees": [{"degree": "B.S.", "year": 1995, "institution": "California Polytechnic State University, San Luis Obispo, Calif."}, {"degree": "M.S.", "year": 1996, "institution": "California Polytechnic State University, San Luis Obispo, Calif."}]}