{"id": "N000002", "update_date": "2018-02-20", "biography_text": "NADLER, Jerrold Lewis, a Representative from New York; born in Brooklyn, Kings County, New York, June 13, 1947; graduated from Stuyvesant High School, New York, N.Y., 1965; B.A., Columbia University, New York, N.Y., 1969; J.D., Fordham University, New York, N.Y., 1978; legislative assistant, New York state assembly, 1972; member of the New York state assembly, 1977-1992; elected as a Democrat to the One Hundred Second Congress, by special election, to fill the vacancy caused by the death of United States Representative Theodore S. Weiss, and to the thirteen succeeding Congresses (November 3, 1992-present).", "name": {"last": "Nadler", "first": "Jerrold", "middle": "Lewis"}, "date_of_birth": {"month": 6, "day": 13, "year": 1947}, "place_of_birth": "Brooklyn, Kings County, New York", "post_secondary_degrees": [{"degree": "B.A.", "year": 1969, "institution": "Columbia University, New York, N.Y."}, {"degree": "J.D.", "year": 1978, "institution": "Fordham University, New York, N.Y."}]}