{"id": "P000608", "update_date": "2017-12-31", "biography_text": "PETERS, Scott, a Representative from California; born in Springfield, Clark County, Ohio, June 17, 1958; B.A., Duke University, Durham, N.C., 1980; J.D., New York University, New York, N.Y., 1984; lawyer, private practice; economist, United States Environmental Protection Agency, 1980-1981; deputy attorney, city of San Diego, Calif., 1991-1996; member of the San Diego, Calif., city council, 2000-2008; president of the San Diego, Calif., city council, 2006-2008; commissioner, San Diego unified port district, 2009-2012; elected as a Democrat to the One Hundred Thirteenth and to the two succeeding Congresses (January 3, 2013-present).", "name": {"last": "Peters", "first": "Scott"}, "date_of_birth": {"month": "June", "day": "17", "year": "1958"}, "place_of_birth": "Springfield, Clark County, Ohio", "post_secondary_degrees": [{"degree": "B.A.", "year": "1980", "institution": "Duke University, Durham, N.C."}, {"degree": "J.D.", "year": "1984", "institution": "New York University, New York, N.Y."}]}