{"id": "P000601", "update_date": "2018-12-23", "biography_text": "PALAZZO, Steven, a Representative from Mississippi; born in Gulfport, Harrison County, Miss., February 21, 1970; graduated from Saint John High School, Gulfport, Miss., 1988; B.S., University of Southern Mississippi, Hattiesburg, Miss., 1994; M.P.A., University of Southern Mississippi, Hattiesburg, Miss., 1996; United States Marine Corps Reserve, 1988-1996; Mississippi Army National Guard, 2007-present; accountant; member of the Mississippi state house of representatives, 2007-2010; elected as a Republican to the One Hundred Twelfth and to the three succeeding Congresses (January 3, 2011-present).", "name": {"last": "Palazzo", "first": "Steven"}, "date_of_birth": {"month": 2, "day": 21, "year": 1970}, "place_of_birth": "Gulfport, Harrison County, Miss.", "post_secondary_degrees": [{"degree": "B.S.", "year": 1994, "institution": "University of Southern Mississippi, Hattiesburg, Miss."}, {"degree": "M.P.A.", "year": 1996, "institution": "University of Southern Mississippi, Hattiesburg, Miss."}]}