{"id": "P000591", "update_date": "2018-12-23", "biography_text": "PRICE, Tom, a Representative from Georgia; born in Lansing, Ingham County, Mich., October 8, 1954; graduated from Dearborn High School, Dearborn, Mich., 1972; A.B., University of Michigan, Ann Arbor, Mich., 1976; M.D., University of Michigan, Ann Arbor, Mich., 1979; physician; member of the Georgia state senate, 1997-2004; elected as a Republican to the One Hundred Ninth and to the six succeeding Congresses until his resignation on February 10, 2017 (January 3, 2005-February 10, 2017); chairman, Committee on Budget (One Hundred Fourteenth Congress); Secretary of Health and Human Services in the Cabinet of President Donald J. Trump, 2017.", "name": {"last": "Price", "first": "Tom"}, "date_of_birth": {"year": 1972}, "place_of_birth": "", "post_secondary_degrees": [{"degree": "A.B.", "year": 1976, "institution": "University of Michigan, Ann Arbor, Mich."}, {"degree": "M.D.", "year": 1979, "institution": "University of Michigan, Ann Arbor, Mich."}]}