{"id": "P000597", "update_date": "2018-02-20", "biography_text": "PINGREE, Chellie, a Representative from Maine; born in Minneapolis, Hennepin County, Minn., April 2, 1955; attended University of Southern Maine, Portland, Maine, 1973; B.A., College of the Atlantic, Bar Harbor, Maine, 1979; farmer; businesswoman; member of the North Haven (Maine) board of assessors, 1981-1987, chairwoman, 1982-1983; member of the North Haven (Maine) planning board, 1981-1991; member of the Maine state senate, 1992-2000, majority leader, 1996-2000; unsuccessful candidate for election to the United States Senate in 2002; elected as a Democrat to the One Hundred Eleventh and to the four succeeding Congresses (January 3, 2009-present). ", "name": {"last": "Pingree", "first": "Chellie"}, "date_of_birth": {"month": 4, "day": 2, "year": 1955}, "place_of_birth": "Minneapolis, Hennepin County, Minn.", "post_secondary_degrees": [{"degree": "B.A.", "year": 1979, "institution": "College of the Atlantic, Bar Harbor, Maine"}]}