{"id": "P000523", "update_date": "2018-01-10", "biography_text": "PRICE, David Eugene, a Representative from North Carolina; born in Erwin, Unicoi County, Tenn., August 17, 1940; graduated from Unicoi County High School, Erwin, Tenn., 1957; attended Mars Hill College, Mars Hill, N.C., 1957-1959; B.A., University of North Carolina, Chapel Hill, N.C., 1961; B.D., Yale University, New Haven, Conn., 1964; Ph.D., Yale University, New Haven, Conn., 1969; faculty, Yale University, New Haven, Conn., 1967-1973; staff, United States Senator Edward Lewis Bartlett of Alaska, 1963-1967; professor, Duke University, Durham, N.C., 1973-1986 and 1995-1996; staff director, commission on presidential nomination, Democratic National Committee, 1981-1982; chairman, North Carolina Democratic Party, 1983-1984; elected as a Democrat to the One Hundredth and to the three succeeding Congresses (January 3, 1987-January 3, 1995); unsuccessful candidate for reelection to the One Hundred Fourth Congress in 1994; elected as a Democrat to the One Hundred Fifth and to the ten succeeding Congresses (January 3, 1997-present). ", "name": {"last": "Price", "first": "David", "middle": "Eugene"}, "date_of_birth": {"month": "August", "day": "17", "year": "1940"}, "place_of_birth": "Erwin, Unicoi County, Tenn.", "post_secondary_degrees": [{"degree": "B.A.", "year": "1961", "institution": "University of North Carolina, Chapel Hill, N.C."}, {"degree": "Ph.D.", "year": "1969", "institution": "Yale University, New Haven, Conn."}]}