{"id": "P000613", "update_date": "2018-02-20", "biography_text": "PANETTA, James Varni,  (son of Leon Panetta), a Representative from California; born in Washington, D.C., October 1, 1969; A.A., Monterey Peninsula College, Monterey, Calif., 1989; B.A. University of California, Davis, Calif., 1991; J.D., Santa Clara University, Santa Clara, Calif., 1996; United States Navy Reserve, 2003-2011; clerk, United States Department of State, 1992; Alameda County, Calif., prosecutor, 1996-2010; Alameda County Calif., deputy district attorney, 1996-2010; Monterey County, Calif., prosecutor, 2010-2016; Monterey County, Calif., deputy district attorney, 2010-2016; Monterey County, Calif., central Democratic committee vice chairman, 2012-2016; elected as a Democrat to the One Hundred Fifteenth Congress (January 3, 2017-present).", "name": {"last": "Panetta", "first": "James", "middle": "Varni"}, "date_of_birth": {"month": 10, "day": 1, "year": 1969}, "place_of_birth": "Washington, D.C.", "post_secondary_degrees": [{"degree": "B.A.", "year": 1991, "institution": "Davis, Calif."}, {"degree": "J.D.", "year": 1996, "institution": "Santa Clara University, Santa Clara, Calif."}]}