{"id": "P000096", "update_date": "2018-12-23", "biography_text": "PASCRELL, William J., Jr., a Representative from New Jersey; born in Paterson, Passaic County, N.J., January 25, 1937; graduated from St. John the Baptist High School, Paterson, N.J., 1955; B.A., Fordham University, New York, N.Y., 1959; M.A., Fordham University, New York, N.Y., 1961; United States Army, 1961-1962; United States Army Reserve, 1962-1967; teacher; president of the Paterson, N.J., board of education, 1979-1982; member of the New Jersey state general assembly, 1988-1996, minority leader pro tempore; mayor of Paterson, N.J., 1990-1996; elected as a Democrat to the One Hundred Fifth and to the ten succeeding Congresses (January 3, 1997-present).", "name": {"last": "Pascrell", "first": "William", "middle": "J."}, "date_of_birth": {"month": 1, "day": 25, "year": 1937}, "place_of_birth": "Paterson, Passaic County, N.J.", "post_secondary_degrees": [{"degree": "B.A.", "year": 1959, "institution": "Fordham University, New York, N.Y."}, {"degree": "M.A.", "year": 1961, "institution": "Fordham University, New York, N.Y."}]}