{"id": "P000588", "update_date": "2018-02-20", "biography_text": "PEARCE, Stevan, a Representative from New Mexico; born in Lamesa, Dawson County, Tex., August 24, 1947; attended the public schools; graduated from Hobbs High School, Hobbs, N.Mex., 1965; B.A., New Mexico State University, Las Cruces, N.Mex., 1970; M.B.A., Eastern New Mexico University, Portales, N.Mex., 1991; United States Air Force, 1970-1976; businessman; member of the New Mexico state house of representatives, 1997-2000; elected as a Republican to the One Hundred Eighth and to the two succeeding Congresses (January 3, 2003-January 3, 2009); was not a candidate for reelection to the One Hundred Eleventh Congress in 2008, but was an unsuccessful candidate for election to the United States Senate; elected as a Republican to the One Hundred Twelfth and to the three succeeding Congresses (January 3, 2011-present).", "name": {"last": "Pearce", "first": "Stevan"}, "date_of_birth": {"month": 8, "day": 24, "year": 1947}, "place_of_birth": "Lamesa, Dawson County, Tex.", "post_secondary_degrees": [{"degree": "B.A.", "year": 1970, "institution": "New Mexico State University, Las Cruces, N.Mex."}, {"degree": "M.B.A.", "year": 1991, "institution": "Eastern New Mexico University, Portales, N.Mex."}]}