{"id": "P000595", "update_date": "2018-01-10", "biography_text": "PETERS, Gary C., a Senator and a Representative from Michigan; born in Pontiac, Oakland County, Mich., December 1, 1958; B.A., Alma College, Alma, Mich., 1980; M.B.A., finance, University of Detroit, Detroit, Mich., 1984; J.D., Wayne State University, Detroit, Mich., 1989; M.A., philosophy, Michigan State University, East Lansing, Mich., 2007; United States Navy Reserve, 1993-2000, 2001-2005, attaining the rank of lieutenant commander; assistant vice president, Merrill Lynch, 1980-1989; vice president, UBS/Paine Webber, 1989-2003; arbitrator, Financial Industry Regulatory Authority; instructor, Oakland University, Rochester, Mich., and Wayne State University, Detroit, Mich.; professor, Central Michigan University; member, Rochester Hills, Mich., city council, 1991-1993; member of the Michigan state senate, 1995-2002; unsuccessful candidate for Michigan state attorney general in 2002; chief administrative officer for the bureau of investments, state of Michigan, 2003; lottery commissioner, state of Michigan, 2003-2007; elected as a Democrat to the One Hundred Eleventh and to the two succeeding Congresses (January 3, 2009-January 3, 2015); was not a candidate for reelection to the House of Representatives but was elected as a Democrat to the United States Senate in 2014 for the term ending January 3, 2021. ", "name": {"last": "Peters", "first": "Gary", "middle": "C."}, "date_of_birth": {"month": "December", "day": "1", "year": "1958"}, "place_of_birth": "Pontiac, Oakland County, Mich.", "post_secondary_degrees": [{"degree": "B.A.", "year": "1980", "institution": "Alma College, Alma, Mich."}, {"degree": "M.B.A.", "year": "1984", "institution": "finance, University of Detroit, Detroit, Mich."}, {"degree": "J.D.", "year": "1989", "institution": "Wayne State University, Detroit, Mich."}, {"degree": "M.A.", "year": "2007", "institution": "philosophy, Michigan State University, East Lansing, Mich."}]}