{"id": "P000610", "update_date": "2017-12-31", "biography_text": "PLASKETT, Stacey E., a Delegate from the Virgin Islands; born in New York, Kings County, New York, May 13, 1966; graduated from Choate Rosemary Hall, Wallingford, Conn., 1984; B.S.F.S., Georgetown University, Washington, D.C., 1988; J.D., American University, Washington, D.C., 1994; lawyer, private practice; professional advocate; staff, United States Delegate Ron de Lugo of the Virgin Islands; Bronx County, N.Y., assistant district attorney, 1994-1997; staff, House Committee on Ethics; staff, United States Department of Justice, 2002-2004; general counsel, Virgin Islands economic development authority, 2007-2014; unsuccessful candidate for nomination to the United States House of Representatives in 2012; elected as a Democrat to the One Hundred Fourteenth and to the succeeding Congress (January 3, 2015-present).", "name": {"last": "Plaskett", "first": "Stacey", "middle": "E."}, "date_of_birth": {"month": "May", "day": "13", "year": "1966"}, "place_of_birth": "New York, Kings County, New York", "post_secondary_degrees": [{"degree": "B.S.", "year": "1988", "institution": "Georgetown University, Washington, D.C."}, {"degree": "J.D.", "year": "1994", "institution": "American University, Washington, D.C."}]}