{"id": "P000197", "update_date": "2018-01-10", "biography_text": "PELOSI, Nancy,  (daughter of Thomas D'Alesandro, Jr.), a Representative from California; born Nancy D\u0092Alesandro in Baltimore, Md., March 26, 1940; graduated from the Institute of Notre Dame, Baltimore, Md., 1958; A.B., Trinity College, 1962; chair, California state Democratic Party, 1981-1983; finance chairman, Democratic Senatorial Campaign Committee, 1985-1986; elected as a Democrat to the One Hundredth Congress, by special election, to fill the vacancy caused by the death of United States Representative Sala Burton of California, and reelected to the fifteen succeeding Congresses (June 2, 1987-present); minority whip (One Hundred Seventh Congress); minority leader (One Hundred Eighth, One Hundred Ninth, and One Hundred Twelfth through One Hundred Fifteenth Congresses); Speaker of the House (One Hundred Tenth and One Hundred Eleventh Congresses). ", "name": {"last": "Pelosi", "first": "Nancy"}, "date_of_birth": {"month": 3, "day": 26, "year": 1940}, "place_of_birth": "Baltimore, Md.", "post_secondary_degrees": [{"degree": "A.B.", "year": 1962, "institution": "Trinity College"}]}