{"id": "Q000023", "update_date": "2017-12-31", "biography_text": "QUIGLEY, Mike, a Representative from Illinois; born in Indianapolis, Marion County, Ind., October 17, 1958; attended Glenbard North High School, Carol Stream, Ill.; B.A., Roosevelt University, Chicago, Ill., 1981; M.P.P., University of Chicago, Chicago, Ill., 1985; J.D., Loyola University School of Law, Chicago, Ill., 1989; professor; lawyer; legislative aide; member of the Cook County, Ill., board of commissioners, 1998-2009; elected as a Democrat to the One Hundred Eleventh Congress, by special election, to fill the vacancy caused by the resignation of United States Representative Rahm Emanuel, and reelected to the four succeeding Congresses (April 7, 2009-present).", "name": {"last": "Quigley", "first": "Mike"}, "date_of_birth": {"month": "October", "day": "17", "year": "1958"}, "place_of_birth": "Indianapolis, Marion County, Ind.", "post_secondary_degrees": [{"degree": "B.A.", "year": "1981", "institution": "Roosevelt University, Chicago, Ill."}, {"degree": "J.D.", "year": "1989", "institution": "Loyola University School of Law, Chicago, Ill."}]}