{"id": "R000435", "update_date": "2018-01-10", "biography_text": "ROS-LEHTINEN, Ileana, a Representative from Florida; born Ileana Ros in Havana, Cuba, July 15, 1952; A.A., Miami-Dade Community College, Miami, Fla., 1972; B.A., Florida International University, Miami, Fla., 1975; M.S., Florida International University, Miami, Fla., 1987; Ed.D., University of Miami, Coral Gables, Fla., 2004; founder, Eastern Academy; member of the Florida state house of representatives, 1982-1986; member of the Florida state senate, 1986-1989; elected as a Republican to the One Hundred First Congress, by special election, to fill the vacancy caused by the death of United States Representative Claude D. Pepper, and reelected to the fourteen succeeding Congresses (August 29, 1989-present); chair, Committee on Foreign Affairs (One Hundred Twelfth Congress).", "name": {"last": "Ros-lehtinen", "first": "Ileana"}, "date_of_birth": {"month": 7, "day": 15, "year": 1952}, "place_of_birth": "Havana, Cuba", "post_secondary_degrees": [{"degree": "B.A.", "year": 1975, "institution": "Florida International University, Miami, Fla."}, {"degree": "M.S.", "year": 1987, "institution": "Florida International University, Miami, Fla."}]}