{"id": "R000600", "update_date": "2018-01-10", "biography_text": "RADEWAGEN, Aumua Amata Coleman, a Delegate from American Samoa; born in Washington, D.C., December 29, 1947; attended Sacred Hearts Academy, Honolulu, Hawaii; B.S., University of Guam, 1975; attended George Mason University, Fairfax, Va.; attended Loyola Marymount University, Los Angeles, Calif.; journalist; staff, United States Representative Philip Crane of Illinois, 1997-1999; staff, United States Representative Julius Caesar (J.C.) Watts, Jr. of Oklahoma, 1999-2003; staff, House Republican Conference, 2003-2005; unsuccessful candidate for election to the One Hundred Fourth Congress in 1994, One Hundred Sixth Congress in 1998, One Hundred Eighth Congress in 2002, One Hundred Ninth Congress in 2004, One Hundred Tenth Congress in 2006, One Hundred Eleventh Congress in 2008, One Hundred Twelfth Congress in 2010, and One Hundred Thirteenth Congress in 2012; unsuccessful candidate for nomination to the One Hundred Fifth Congress in 1996 and One Hundred Seventh Congress in 2000; elected as a Republican to the One Hundred Fourteenth and to the succeeding Congress (January 3, 2015-present).", "name": {"last": "Radewagen", "first": "Aumua", "middle": "Amata Coleman"}, "date_of_birth": {"month": 12, "day": 29, "year": 1947}, "place_of_birth": "Washington, D.C.", "post_secondary_degrees": [{"degree": "B.S.", "year": 1975, "institution": "University of Guam"}]}