{"id": "R000592", "update_date": "2018-01-10", "biography_text": "ROKITA, Todd, a Representative from Indiana; born in Chicago, Cook County, Ill., February 9, 1970; graduated from Munster High School, Munster, Ind., 1988; B.A., Wabash College, Crawfordsville, Ind., 1992; J.D., Robert H. McKinney School of Law, Indiana University, Indianapolis, Ind., 1995; lawyer, private practice; general counsel, Indiana state secretary of state\u0092s office, 1997-2000; Indiana state deputy secretary of state, 2000-2002; Indiana state secretary of state, 2002-2010; elected as a Republican to the One Hundred Twelfth and to the three succeeding Congresses (January 3, 2011-present).", "name": {"last": "Rokita", "first": "Todd"}, "date_of_birth": {"month": "February", "day": "9", "year": "1970"}, "place_of_birth": "Chicago, Cook County, Ill.", "post_secondary_degrees": [{"degree": "B.A.", "year": "1992", "institution": "Wabash College, Crawfordsville, Ind."}, {"degree": "J.D.", "year": "1995", "institution": "Robert H. McKinney School of Law, Indiana University, Indianapolis, Ind."}]}