{"id": "R000582", "update_date": "2018-02-20", "biography_text": "ROE, David P. (Phil), a Representative from Tennessee, born in Clarksville, Montgomery County, Tenn., July 21, 1945; B.S., Austin Peay State University, Clarksville, Tenn., 1967; M.D., University of Tennessee, Knoxville, Tenn., 1970; United States Army, 1973-1974; physician; unsuccessful candidate for nomination to the One Hundred Tenth Congress in 2006; member of the Johnson City, Tenn., board of commissioners, 2003-2008; vice mayor of Johnson City, Tenn., 2003-2007; Mayor of Johnson City, Tenn., 2007-2009; elected as a Republican to the One Hundred Eleventh and to the four succeeding Congresses (January 3, 2009-present); chair, Committee on Veterans\u0092 Affairs (One Hundred Fifteenth Congress).", "name": {"last": "Roe", "first": "David", "middle": "P.", "nickname": "Phil"}, "date_of_birth": {"month": 7, "day": 21, "year": 1945}, "place_of_birth": "Clarksville, Montgomery County, Tenn.", "post_secondary_degrees": [{"degree": "B.S.", "year": 1967, "institution": "Austin Peay State University, Clarksville, Tenn."}, {"degree": "M.D.", "year": 1970, "institution": "University of Tennessee, Knoxville, Tenn."}]}