{"id": "R000575", "update_date": "2017-12-31", "biography_text": "ROGERS, Mike Dennis, a Representative from Alabama; born in Hammond, Lake County, Ind., July 16, 1958; graduated from Saks High School, Anniston, Ala., 1976; B.A., Jacksonville State University, Jacksonville, Ala., 1981; M.P.A., Jacksonville State University, Jacksonville, Ala., 1984; J.D., Birmingham School of Law, Birmingham, Ala., 1991; member of the Calhoun County, Ala., commission, 1987-1990; member of the Alabama state house of representatives, 1994-2002, minority leader, 1998-2000; elected as a Republican to the One Hundred Eighth and to the seven succeeding Congresses (January 3, 2003-present).", "name": {"last": "Rogers", "first": "Mike", "middle": "Dennis"}, "date_of_birth": {"month": "July", "day": "16", "year": "1958"}, "place_of_birth": "Hammond, Lake County, Ind.", "post_secondary_degrees": [{"degree": "B.A.", "year": "1981", "institution": "Jacksonville State University, Jacksonville, Ala."}, {"degree": "M.P.A.", "year": "1984", "institution": "Jacksonville State University, Jacksonville, Ala."}, {"degree": "J.D.", "year": "1991", "institution": "Birmingham School of Law, Birmingham, Ala."}]}