{"id": "R000610", "update_date": "2019-01-04", "biography_text": "RESCHENTHALER, Guy, a Representative from Pennsylvania; born on April 17, 1983; graduated from Thomas Jefferson High School, Jefferson Hills, Pa., 2001; B.A., Pennsylvania State University Behrend College, Erie, Pa., 2004; J.D., Duquesne University, Pittsburgh, Pa., 2007; United States Navy, 2007-2012; lawyer, private practice; Pennsylvania state magisterial district judge, 2013-2015; member of the Pennsylvania state senate, 2015-2018; unsuccessful candidate for nomination to the One Hundred Fifteenth Congress in a special election in 2017;elected as a Republican to the One Hundred Sixteenth Congress (January 3, 2019-present).", "name": {"last": "Reschenthaler", "first": "Guy"}, "date_of_birth": {"month": 4, "day": 17, "year": 1983}, "place_of_birth": "", "post_secondary_degrees": [{"degree": "B.A.", "year": 2004, "institution": "Pennsylvania State University Behrend College, Erie, Pa."}, {"degree": "J.D.", "year": 2007, "institution": "Duquesne University, Pittsburgh, Pa."}]}