{"id": "R000598", "update_date": "2017-12-31", "biography_text": "ROTHFUS, Keith, a Representative from Pennsylvania; born in Endicott, Broome County, N.Y., April 25, 1962; graduated from West Seneca West Senior High School, West Seneca, N.Y., 1980; B.S., State University of New York-Buffalo State, Buffalo, N.Y., 1984; J.D., University of Notre Dame, Notre Dame, Ind., 1990; lawyer, private practice; director, Center for Faith-Based and Community Initiatives, United States Department of Homeland Security, 2006-2007; unsuccessful candidate for election to the One Hundred Twelfth Congress in 2010; elected as a Republican to the One Hundred Thirteenth and to the two succeeding Congresses (January 3, 2013-present).", "name": {"last": "Rothfus", "first": "Keith"}, "date_of_birth": {"month": "April", "day": "25", "year": "1962"}, "place_of_birth": "Endicott, Broome County, N.Y.", "post_secondary_degrees": [{"degree": "B.S.", "year": "1984", "institution": "State University of New York-Buffalo State, Buffalo, N.Y."}, {"degree": "J.D.", "year": "1990", "institution": "University of Notre Dame, Notre Dame, Ind."}]}