{"id": "R000576", "update_date": "2018-01-10", "biography_text": "RUPPERSBERGER, C. A. (Dutch), a Representative from Maryland; born in Baltimore, Md., on January 31, 1946; graduated from Baltimore City College, Baltimore, Md., 1963; attended University of Maryland, College Park, Md.; J.D., University of Baltimore School of Law, Baltimore, Md., 1970; lawyer, private practice; assistant Maryland state\u0092s attorney, 1972-1980; member of the Baltimore County, Md., county council, 1985-1994; delegate, Democrat National Convention, 1996 and 2000; Baltimore, Md., county executive, 1994-2002; elected as a Democrat to the One Hundred Eighth and to the seven succeeding Congresses (January 3, 2003-present).", "name": {"last": "Ruppersberger", "first": "C.", "middle": "A.", "nickname": "Dutch"}, "date_of_birth": {"month": 1, "day": 31, "year": 1946}, "place_of_birth": "", "post_secondary_degrees": [{"degree": "J.D.", "year": 1970, "institution": "University of Baltimore School of Law, Baltimore, Md."}]}