{"id": "R000584", "update_date": "2018-01-10", "biography_text": "RISCH, James, a Senator from Idaho; born in Milwaukee, Wis., May 3, 1943; B.A., attended the University of Wisconsin, Milwaukee, 1961-1963; B.S. in Forestry, University of Idaho, 1965; J.D., University of Idaho College of Law, 1968; Ada County, Idaho, prosecuting attorney, 1970-1974; Idaho State senator, 1974-1989 and 1995-2003, serving as majority leader (1976-1982), and as president pro tempore (1982-1989); lieutenant governor of Idaho, 2003-2006 and 2007-2009; governor of Idaho, 2006; elected as a Republican to the United States Senate in 2008; reelected in 2014 for the term ending January 3, 2021; chair, Committee on Small Business and Entrepreneurship (One Hundred Fifteenth Congress).", "name": {"last": "Risch", "first": "James"}, "date_of_birth": {"month": "May", "day": "3", "year": "1943"}, "place_of_birth": "Milwaukee, Wis.", "post_secondary_degrees": [{"degree": "B.A.", "year": "1961", "institution": "attended the University of Wisconsin, Milwaukee"}, {"degree": "B.S.", "year": "1965", "institution": "University of Idaho"}, {"degree": "J.D.", "year": "1968", "institution": "University of Idaho College of Law"}]}