{"id": "R000122", "update_date": "2018-01-10", "biography_text": "REED, John F. (Jack), a Senator and a Representative from Rhode Island; born in Providence, R.I., November 12, 1949; attended St. Matthew\u0092s Elementary School, Cranston, R.I.; graduated, LaSalle Academy, Providence, R.I., 1967; B.S., United States Military Academy, West Point 1971; M.P.P., Kennedy School of Government, Harvard University 1973; J.D., Harvard Law School 1982; served in the U.S. Army 1971-1979 and Army Reserve 1979-1991; associate professor, Department of Social Sciences, U.S. Military Academy 1977-1979; admitted to the Washington, D.C. bar 1983; lawyer; member, Rhode Island State senate 1985-1990; elected as a Democrat to the One Hundred Second and to the two succeeding Congresses (January 3, 1991-January 2, 1997); was not a candidate for reelection to the House of Representatives in 1996, but was elected to the United States Senate in 1996; reelected in 2002, 2008, and again in 2014 for the term ending January 3, 2021. ", "name": {"last": "Reed", "first": "John", "middle": "F.", "nickname": "Jack"}, "date_of_birth": {"month": 11, "day": 12, "year": 1949}, "place_of_birth": "Providence, R.I.", "post_secondary_degrees": [{"degree": "B.S.", "year": 1971, "institution": "United States Military Academy"}, {"degree": "J.D.", "year": 1982, "institution": ""}]}