{"id": "R000583", "update_date": "2018-12-23", "biography_text": "ROONEY, Thomas J., a Representative from Florida; born in Philadelphia, Philadelphia County, Pa., November 21, 1970; attended Syracuse University, Syracuse, N.Y., 1989; B.A., Washington and Jefferson College, Washington, Pa., 1993; M.A., University of Florida, Gainesville, Fla., 1996; J.D., University of Miami, Coral Gables, Fla., 1999; United States Army, 2000-2004; lawyer, private practice; assistant attorney general, Office of the Attorney General, State of Florida; professor, United States Military Academy, West Point, N.Y.; staff, United States Senator Connie Mack III of Florida; elected as a Republican to the One Hundred Eleventh and to the four succeeding Congresses (January 3, 2009-present). ", "name": {"last": "Rooney", "first": "Thomas", "middle": "J."}, "date_of_birth": {"month": 11, "day": 21, "year": 1970}, "place_of_birth": "Philadelphia, Philadelphia County, Pa.", "post_secondary_degrees": [{"degree": "B.A.", "year": 1993, "institution": "Washington and Jefferson College, Washington, Pa."}, {"degree": "M.A.", "year": 1996, "institution": "University of Florida, Gainesville, Fla."}, {"degree": "J.D.", "year": 1999, "institution": "University of Miami, Coral Gables, Fla."}]}