{"id": "R000599", "update_date": "2018-02-20", "biography_text": "RUIZ, Raul, a Representative from California; born in Zacatecas, Mexico, August 25, 1972; graduated from Coachella Valley High School, Coachella, Calif., 1990; B.S., University of California, Los Angeles, Calif., 1994; M.D., Harvard University, Cambridge, Mass., 2001; M.P.P., Harvard University, Cambridge, Mass., 2001; M.P.H., Harvard University, Cambridge, Mass., 2007; physician; associate dean, University of California-Riverside School of Medicine, Riverside, Calif., 2011-2012; elected as a Democrat to the One Hundred Thirteenth and to the two succeeding Congresses (January 3, 2013-present).", "name": {"last": "Ruiz", "first": "Raul"}, "date_of_birth": {"month": 8, "day": 25, "year": 1972}, "place_of_birth": "Zacatecas, Mexico", "post_secondary_degrees": [{"degree": "B.S.", "year": 1994, "institution": "University of California, Los Angeles, Calif."}, {"degree": "M.D.", "year": 2001, "institution": "Harvard University, Cambridge, Mass."}, {"degree": "M.P.H.", "year": 2007, "institution": "Harvard University, Cambridge, Mass."}]}