{"id": "S000364", "update_date": "2018-02-20", "biography_text": "SHIMKUS, John M., a Representative from Illinois; born in Collinsville, Madison County, Ill., February 21, 1958; graduated from Collinsville High School, Collinsville, Ill.; B.S., United States Military Academy, West Point, N.Y., 1980; teaching certificate, Christ College, Irvine, Calif., 1990; M.B.A., Southern Illinois University, Edwardsville, Ill., 1997; United States Army, 1980-1986; United States Army Reserve, 1986-2008; Collinsville Township, Ill., trustee, 1989-1993; Madison County, Ill., treasurer, 1990-1996; elected as a Republican to the One Hundred Fifth and to the ten succeeding Congresses (January 3, 1997-present).", "name": {"last": "Shimkus", "first": "John", "middle": "M."}, "date_of_birth": {"month": 2, "day": 21, "year": 1958}, "place_of_birth": "Collinsville, Madison County, Ill.", "post_secondary_degrees": [{"degree": "B.S.", "year": 1980, "institution": "United States Military Academy, West Point, N.Y."}, {"degree": "M.B.A.", "year": 1997, "institution": "Southern Illinois University, Edwardsville, Ill."}]}