{"id": "S000480", "update_date": "2018-01-10", "biography_text": "SLAUGHTER, Louise McIntosh, a Representative from New York; born Louise McIntosh in Harlan County, Ky., August 14, 1929; graduated from Somerset High School, Somerset, Ky., 1947; B.S., University of Kentucky, Lexington, Ky., 1951; M.S., University of Kentucky, Lexington, Ky., 1953; elected to the Monroe County, N.Y., legislature, 1976-1979; regional coordinator for New York department of state, 1976-1979; coordinator, regional office of New York lieutenant governor, 1979-1982; member of the New York state assembly, 1982-1986; elected as a Democrat to the One Hundredth and to the fifteen succeeding Congresses (January 3, 1987-present); chair, Committee on Rules (One Hundred Tenth and One Hundred Eleventh Congresses).", "name": {"last": "Slaughter", "first": "Louise", "middle": "McIntosh"}, "date_of_birth": {"month": "August", "day": "14", "year": "1929"}, "place_of_birth": "Harlan County, Ky.", "post_secondary_degrees": [{"degree": "B.S.", "year": "1951", "institution": "University of Kentucky, Lexington, Ky."}, {"degree": "M.S.", "year": "1953", "institution": "University of Kentucky, Lexington, Ky."}]}