{"id": "S000770", "update_date": "2018-01-10", "biography_text": "STABENOW, Deborah Ann, a Senator and a Representative from Michigan; born in Gladwin, Mich., April 29, 1950; graduated, Clare High School; B.A., Michigan State University, East Lansing 1972; M.S.W. magna cum laude, Michigan State University, 1975; social worker; leadership training consultant; Ingham County commissioner 1975-1978; member, State house of representatives 1979-1990; member, State senate 1991-1994; elected as a Democrat to the One Hundred Fifth and One Hundred Sixth Congresses (January 3, 1997-January 3, 2001); was not a candidate for reelection to the House of Representatives in 2000, but was elected to the United States Senate for the term commencing January 3, 2001; reelected in 2006 and again in 2012 for the term ending January 3, 2019; Democratic Conference secretary (2005-2007); vice-chair, Democratic Policy and Communications Committee (2011-2017); chair, Democratic Policy and Communications Committee (2017-); chair, Committee on Agriculture, Nutrition, and Forestry (One Hundred Twelfth and One Hundred Thirteenth Congresses). ", "name": {"last": "Stabenow", "first": "Deborah", "middle": "Ann"}, "date_of_birth": {"month": 4, "day": 29, "year": 1950}, "place_of_birth": "Gladwin, Mich.", "post_secondary_degrees": [{"degree": "B.A.", "year": 1972, "institution": "Michigan State University"}, {"degree": "M.S.", "year": 1975, "institution": "Michigan State University"}]}