{"id": "S000185", "update_date": "2017-12-31", "biography_text": "SCOTT, Robert C., a Representative from Virginia; born in Washington, D.C., April 30, 1947; graduated from Groton School, Groton, Mass., 1965; A.B., Harvard University, Cambridge, Mass., 1969; J.D., Boston College School of Law, Boston, Mass., 1973; lawyer, private practice; United States Army Reserve, 1970-1974; Massachusetts Army National Guard, 1974-1976; member of the Virginia state house of delegates, 1978-1983; member of the Virginia state senate, 1983-1993; unsuccessful candidate for election to the One Hundredth Congress in 1986; elected as a Democrat to the One Hundred Third and to the twelve succeeding Congresses (January 3, 1993-present).", "name": {"last": "Scott", "first": "Robert", "middle": "C."}, "date_of_birth": {"month": "April", "day": "30", "year": "1947"}, "place_of_birth": "Washington, D.C.", "post_secondary_degrees": [{"degree": "A.B.", "year": "1969", "institution": "Harvard University, Cambridge, Mass."}, {"degree": "J.D.", "year": "1973", "institution": "Boston College School of Law, Boston, Mass."}]}