{"id": "S001175", "update_date": "2018-01-10", "biography_text": "SPEIER, Karen Lorraine Jacqueline (Jackie), a Representative from California; born in San Francisco, San Francisco County, Calif., May 14, 1950; graduated from Mercy High School, Burlingame, Calif., 1968; B.A., University of California, Davis, Calif., 1972; J.D., University of California Hastings School of Law, San Francisco, Calif., 1976; staff, United States Representative Leo Joseph Ryan of California, 1973-1978; lawyer, private practice; San Mateo County, Calif., supervisor, 1980-1986; member of the California state assembly, 1986-1998; member of the California state senate, 1998-2006; unsuccessful candidate for the special election to fill the vacancy caused by the death of United States Representative Leo Joseph Ryan of California in 1979; unsuccessful candidate for election for lieutenant governor of California in 2006;elected as a Democrat to the One Hundred Tenth Congress, by special election, to fill the vacancy caused by the death of United States Representative Thomas Peter Lantos, and reelected to the five succeeding Congresses (April 8, 2008-present). ", "name": {"last": "Speier", "first": "Karen", "middle": "Lorraine Jacqueline", "nickname": "Jackie"}, "date_of_birth": {"month": "May", "day": "14", "year": "1950"}, "place_of_birth": "San Francisco, San Francisco County, Calif.", "post_secondary_degrees": [{"degree": "B.A.", "year": "1972", "institution": "University of California, Davis, Calif."}, {"degree": "J.D.", "year": "1976", "institution": "University of California Hastings School of Law, San Francisco, Calif."}]}