{"id": "S001165", "update_date": "2018-12-23", "biography_text": "SIRES, Albio, a Representative from New Jersey; born in Bejucal, Cuba, January 26, 1951; graduated from Memorial High School, West New York, N.J., 1970; B.A., St. Peter\u2019s College, Jersey City, N.J., 1974; M.A., Middlebury College, Middlebury, Vt., 1985; businessman; teacher; unsuccessful candidate for election to the One Hundredth Congress in 1986; Mayor of West New York, N.J., 1995- 2007; member of the New Jersey state general assembly, 2000-2006, speaker, 2002-2006; elected as a Democrat to the One Hundred Ninth Congress, by special election, to fill the vacancy caused by the resignation of United States Representative Robert Menendez, and reelected to the six succeeding Congresses (November 7, 2006-present).", "name": {"last": "Sires", "first": "Albio"}, "date_of_birth": {"month": 1, "day": 26, "year": 1951}, "place_of_birth": "Bejucal, Cuba", "post_secondary_degrees": [{"degree": "B.A.", "year": 1974, "institution": "St. Peter\u2019s College, Jersey City, N.J."}, {"degree": "M.A.", "year": 1985, "institution": "Middlebury College, Middlebury, Vt."}]}