{"id": "S001176", "update_date": "2018-01-10", "biography_text": "SCALISE, Steve, a Representative from Louisiana; born in New Orleans, Orleans Parish, La., October 6, 1965; graduated from Rummel High School; B.S., Louisiana State Univeristy, Baton Rouge, La.; software engineer; technology company marketing executive; member of the Louisiana state house of representatives, 1995-2007; member of the Louisiana state senate, 2008; elected as a Republican to the One Hundred Tenth Congress, by special election, to fill the vacancy caused by the resignation of United States Representative Bobby Jindal, and reelected to the five succeeding Congresses (May 3, 2008-present); majority whip (One Hundred Thirteenth through One Hundred Fifteenth Congresses).", "name": {"last": "Scalise", "first": "Steve"}, "date_of_birth": {"month": 10, "day": 6, "year": 1965}, "place_of_birth": "New Orleans, Orleans Parish, La.", "post_secondary_degrees": [{"degree": "B.S.", "institution": "Louisiana State Univeristy, Baton Rouge, La."}]}