{"id": "S001154", "update_date": "2018-12-23", "biography_text": "SHUSTER, William (Bill),  (son of E. G. \"Bud\" Shuster), a Representative from Pennsylvania; born in McKeesport, Allegheny County, Pa., January 10, 1961; graduated from Everett High School, Everett. Pa.; B.A., Dickinson College, Carlisle, Pa., 1983; M.B.A., American University, Washington, D.C.; business owner; elected as a Republican to the One Hundred Seventh Congress, by special election, to fill the vacancy caused by the resignation of United States Representative E. G. \u0093Bud\u0094 Shuster of Pennsylvania and reelected to the eight succeeding Congresses (May 15, 2001-present); chair, Committee on Transportation and Infrastructure (One Hundred Thirteenth through One Hundred Fifteenth Congresses).", "name": {"last": "Shuster", "first": "William", "nickname": "Bill"}, "date_of_birth": {"month": 1, "day": 10, "year": 1961}, "place_of_birth": "McKeesport, Allegheny County, Pa.", "post_secondary_degrees": [{"degree": "B.A.", "year": 1983, "institution": "Dickinson College, Carlisle, Pa."}, {"degree": "M.B.A.", "institution": "American University, Washington, D.C."}]}