{"id": "S001197", "update_date": "2019-01-04", "biography_text": "SASSE, Benjamin Eric, a Senator from Nebraska; born in Plainview, Pierce County, Nebr., February 22, 1972; B.A., Harvard University, 1994; M.A., St. John\u2019s College, Annapolis, Md., 1998; Ph.D., Yale University, 2004; management consultant; university professor; chief of staff to U.S. Representative Jeff Fortenberry; counselor to the secretary, U.S. Department of Health and Human Services; assistant secretary for planning and evaluation, U.S. Department of Health and Human Services; president of Midland University, Fremont, Nebr.; elected as a Republican to the United States Senate in 2014 for the term ending January 3, 2021. ", "name": {"last": "Sasse", "first": "Benjamin", "middle": "Eric"}, "date_of_birth": {"month": 2, "day": 22, "year": 1972}, "place_of_birth": "Plainview, Pierce County, Nebr.", "post_secondary_degrees": [{"degree": "B.A.", "year": 1994, "institution": "Harvard University"}, {"degree": "M.A.", "year": 1998, "institution": "St. John\u2019s College, Annapolis, Md."}, {"degree": "Ph.D.", "year": 2004, "institution": "Yale University"}]}