{"id": "S001207", "update_date": "2019-01-04", "biography_text": "SHERRILL, Mikie, a Representative from New Jersey; born in Alexandria, Va., January 19, 1972; graduated from South Lakes High School, Reston, Va., 1990; B.S., United States Naval Academy, Annapolis, Md., 1994; M.A., London School of Economics and Political Science, London, England, 2003; J.D., Georgetown University; Washington, D.C., 2007; United States Navy, 1994-2003; lawyer; staff, United States Attorney for the District of New Jersey, 2012-2015; Assistant United States Attorney for the District of New Jersey, 2015-2016; elected as a Democrat to the One Hundred Sixteenth Congress (January 3, 2019-present). ", "name": {"last": "Sherrill", "first": "Mikie"}, "date_of_birth": {"month": 1, "day": 19, "year": 1972}, "place_of_birth": "Alexandria, Va.", "post_secondary_degrees": [{"degree": "B.S.", "year": 1994, "institution": "United States Naval Academy, Annapolis, Md."}, {"degree": "M.A.", "year": 2003, "institution": "London School of Economics and Political Science, London, England"}, {"degree": "J.D.", "institution": "Georgetown University"}]}