{"id": "S001208", "update_date": "2019-01-04", "biography_text": "SLOTKIN, Elissa, a Representative from Michigan; born in Holly, Oakland County, Mich., July 10, 1976; graduated from the Cranbrook Schools, Bloomfield Hills, Mich., 1994; A.B., Cornell University, Ithaca, N.Y., 1998; M.A., Columbia University, New York, N.Y., 2003; staff, nonprofit organization; consultant; analyst, Central Intelligence Agency, 2003-2005, 2006-2007; staff, Office of the Director of National Intelligence, 2005-2006; staff, National Security Council, 2007-2009; staff, United States Department of State, 2009-2011; staff, United States Department of Defense, 2011-2015; Acting Assistant Secretary of Defense, 2015-2017; elected as a Democrat to the One Hundred Sixteenth Congress (January 3, 2019-present). ", "name": {"last": "Slotkin", "first": "Elissa"}, "date_of_birth": {"month": 7, "day": 10, "year": 1976}, "place_of_birth": "Holly, Oakland County, Mich.", "post_secondary_degrees": [{"degree": "A.B.", "year": 1998, "institution": "Cornell University, Ithaca, N.Y."}, {"degree": "M.A.", "year": 2003, "institution": "Columbia University, New York, N.Y."}]}