{"id": "S001187", "update_date": "2019-01-04", "biography_text": "STIVERS, Steve, a Representative from Ohio; born in Cincinnati, Hamilton County, Ohio, March 24, 1965; graduated from Ripley-Union-Lewis High School, Ripley, Ohio, 1983; B.A., Ohio State University, Columbus, Ohio, 1989; M.B.A., Ohio State University, Columbus, Ohio, 1996; M.A., Army War College, Carlisle, Pa., 2012; Ohio Army National Guard, 1988-present; brigadier general; staff, Ohio state senate; professional advocate; businessman; member of the Ohio state senate, 2003-2008; unsuccessful candidate for election to the One Hundred Eleventh Congress in 2008; elected as a Republican to the One Hundred Twelfth and to the four succeeding Congresses (January 3, 2011-present). ", "name": {"last": "Stivers", "first": "Steve"}, "date_of_birth": {"month": 3, "day": 24, "year": 1965}, "place_of_birth": "Cincinnati, Hamilton County, Ohio", "post_secondary_degrees": [{"degree": "B.A.", "year": 1989, "institution": "Ohio State University, Columbus, Ohio"}, {"degree": "M.B.A.", "year": 1996, "institution": "Ohio State University, Columbus, Ohio"}, {"degree": "M.A.", "year": 2012, "institution": "Army War College, Carlisle, Pa."}]}