{"id": "S001195", "update_date": "2019-01-04", "biography_text": "SMITH, Jason, a Representative from Missouri; born in St. Louis, Mo., on June 16, 1980; graduated from Salem High School, Salem, Mo., 1998; B.S., University of Missouri, Columbia, Mo., 2001; J.D., Oklahoma City University School of Law, Oklahoma City, Oklahoma, 2004; farmer; lawyer, private practice; member of the Missouri state house of representatives, 2005-2013; elected as a Republican to the One Hundred Thirteenth Congress, by special election, to fill the vacancy caused by the resignation of United States Representative Jo Ann Emerson, and reelected to the three succeeding Congresses (June 4, 2013-present). ", "name": {"last": "Smith", "first": "Jason"}, "date_of_birth": {"month": 6, "day": 16, "year": 1980}, "place_of_birth": "", "post_secondary_degrees": [{"degree": "B.S.", "year": 2001, "institution": "University of Missouri, Columbia, Mo."}, {"degree": "J.D.", "year": 2004, "institution": "Oklahoma City University School of Law, Oklahoma City, Oklahoma"}]}