{"id": "S001183", "update_date": "2018-12-23", "biography_text": "SCHWEIKERT, David, a Representative from Arizona; born in Los Angeles, Los Angeles County, Calif., on March 3, 1962; A.A., Scottsdale Community College, Scottsdale, Ariz., 1985; B.S., Arizona State University, Tempe, Ariz., 1988; M.B.A., Arizona State University, Tempe, Ariz., 2005; business owner; realtor; financial consultant; member of the Arizona state house of representatives, 1989-1994; member of the Arizona state board of equalization, 1995-2003; Maricopa County, Ariz. treasurer, 2004-2006; elected as a Republican to the One Hundred Twelfth and to the three succeeding Congresses (January 3, 2011-present).", "name": {"last": "Schweikert", "first": "David"}, "date_of_birth": {"month": 3, "day": 3, "year": 1962}, "place_of_birth": "", "post_secondary_degrees": [{"degree": "B.S.", "year": 1988, "institution": "Arizona State University, Tempe, Ariz."}, {"degree": "M.B.A.", "year": 2005, "institution": "Arizona State University, Tempe, Ariz."}]}