{"id": "S001205", "update_date": "2019-01-04", "biography_text": "SCANLON, Mary Gay, a Representative from Pennsylvania; born in Watertown, Jefferson County, N.Y., August 30, 1959; graduated from Watertown High School, Watertown, N.Y., 1976; B.A., Colgate University, Hamilton, N.Y., 1980; J.D., University of Pennsylvania, Philadelphia, Pa., 1984; lawyer, private practice; judicial law clerk, superior court of Pennsylvania; elected simultaneously as a Democrat to the One Hundred Fifteenth and the One Hundred Sixteenth Congresses, by special election, to fill the vacancy caused by the resignation of United States Representative Patrick Meehan (November 6, 2018-present).", "name": {"last": "Scanlon", "first": "Mary", "middle": "Gay"}, "date_of_birth": {"month": 8, "day": 30, "year": 1959}, "place_of_birth": "Watertown, Jefferson County, N.Y.", "post_secondary_degrees": [{"degree": "B.A.", "year": 1980, "institution": "Colgate University, Hamilton, N.Y."}, {"degree": "J.D.", "year": 1984, "institution": "University of Pennsylvania, Philadelphia, Pa."}]}