{"id": "S001206", "update_date": "2019-01-04", "biography_text": "SHALALA, Donna, a Representative from Florida; born in Cleveland, Cuyahoga County, Ohio, February 14, 1941; graduated from West Technical High School, Cleveland, Ohio, 1958; A.B., Western College for Women, Oxford, Ohio, 1962; Ph.D., Syracuse University, Syracuse, N.Y., 1970; United States Peace Corps, 1962-1964; director, Municipal Assistance Corps, New York City, N.Y., 1975-1977; assistant secretary, Department of Housing and Urban Development, 1977-1980; president, Hunter College of the City University of New York, New York City, N.Y., 1980-1988; chancellor, University of Wisconsin-Madison, Madison, Wis., 1988-1993; Secretary of Health and Human Services in the Cabinet of President William J. Clinton, 1993-2001; president, University of Miami, Miami, Fla., 2001-2015; nonprofit executive; elected as a Democrat to the One Hundred Sixteenth Congress (January 3, 2019-present). ", "name": {"last": "Shalala", "first": "Donna"}, "date_of_birth": {"month": 2, "day": 14, "year": 1941}, "place_of_birth": "Cleveland, Cuyahoga County, Ohio", "post_secondary_degrees": [{"degree": "A.B.", "year": 1962, "institution": "Western College for Women, Oxford, Ohio"}, {"degree": "Ph.D.", "year": 1970, "institution": "Syracuse University, Syracuse, N.Y."}]}