{"id": "S001203", "update_date": "2019-01-04", "biography_text": "SMITH, Tina, a Senator from Minnesota; born in Albuquerque, N.Mex., March 4, 1958; B.A., Stanford University, 1980; M.B.A., Dartmouth College, Tuck School of Business, 1984; marketing consultant and executive; chief of staff to Minneapolis mayor R.T. Rybak; chief of staff to Minnesota governor Mark Dayton; lieutenant governor of Minnesota 2015-2018; appointed as a Democrat to the United States Senate to fill the vacancy caused by the resignation of Al Franken, took the oath of office on January 3, 2018; subsequently elected in a special election on November 6, 2018, for the remainder of the term ending January 3, 2021. ", "name": {"last": "Smith", "first": "Tina"}, "date_of_birth": {"month": 3, "day": 4, "year": 1958}, "place_of_birth": "Albuquerque, N.Mex.", "post_secondary_degrees": [{"degree": "B.A.", "year": 1980, "institution": "Stanford University"}, {"degree": "M.B.A.", "year": 1984, "institution": "Dartmouth College, Tuck School of Business"}]}