{"id": "S001150", "update_date": "2018-12-23", "biography_text": "SCHIFF, Adam,  a Representative from California; born in Framingham, Norfolk County, Mass., June 22, 1960; B.A., Stanford University, Stanford, Calif., 1982; J.D., Harvard University, Cambridge, Mass., 1985; lawyer, private practice; prosecutor, Office of the United States Attorney for the Central District of California, 1987-1993; unsuccessful candidate for election to the California state assembly in 1994; member of the California state senate, 1996-2001; elected as a Democrat to the One Hundred Seventh and to the eight succeeding Congresses (January 3, 2001-present); one of the managers appointed by the House of Representatives in 2009 to conduct the impeachment proceedings of Samuel B. Kent, judge of the United States District Court for the Southern District of Texas.", "name": {"last": "Schiff", "first": "Adam"}, "date_of_birth": {"month": 6, "day": 22, "year": 1960}, "place_of_birth": "Framingham, Norfolk County, Mass.", "post_secondary_degrees": [{"degree": "B.A.", "year": 1982, "institution": "Stanford University, Stanford, Calif."}, {"degree": "J.D.", "year": 1985, "institution": "Harvard University, Cambridge, Mass."}]}