{"id": "S001170", "update_date": "2018-01-10", "biography_text": "SHEA-PORTER, Carol, a Representative from New Hampshire; born in New York City, New York County, N.Y., December, 1952; graduated from Oyster River High School, Durham, N.H., 1971; B.A., University of New Hampshire, Durham, N.H., 1975; M.P.A., University of New Hampshire, Durham, N.H., 1979; social worker; professor; elected as a Democrat to the One Hundred Tenth and to the succeeding Congress (January 3, 2007-January 3, 2011); unsuccessful candidate for reelection to the One Hundred Twelfth Congress in 2010; elected as a Democrat to the One Hundred Thirteenth Congress (January 3, 2013-January 3, 2015); unsuccessful candidate for reelection to the One Hundred Fourteenth Congress in 2014; elected as a Democrat to the One Hundred Fifteenth Congress (January 3, 2017-present).", "name": {"last": "Shea-porter", "first": "Carol"}, "date_of_birth": {"year": 1952}, "place_of_birth": "New York City, New York County, N.Y.", "post_secondary_degrees": [{"degree": "B.A.", "year": 1975, "institution": "University of New Hampshire, Durham, N.H."}, {"degree": "M.P.A.", "year": 1979, "institution": "University of New Hampshire, Durham, N.H."}]}