{"id": "T000468", "update_date": "2019-01-04", "biography_text": "TITUS, Alice (Dina), a Representative from Nevada; born in Thomasville, Thomas County, Ga., May 23, 1950; A.B., College of William and Mary, Williamsburg, Va., 1970; M.A., University of Georgia, Athens, Ga., 1973; Ph.D., Florida State University, Tallahassee, Fla., 1976; professor, University of Nevada, Las Vegas, Nev., 1977-2011; member of the Nevada state senate, 1989-2008, minority leader, 1993-2008; unsuccessful candidate for Governor of Nevada, 2006; elected as a Democrat to the One Hundred Eleventh Congress (January 3, 2009-January 3, 2011); unsuccessful candidate for reelection to the One Hundred Twelfth Congress in 2010; elected as a Democrat to the One Hundred Thirteenth and to the three succeeding Congresses (January 3, 2013-present). ", "name": {"last": "Titus", "first": "Alice", "nickname": "Dina"}, "date_of_birth": {"month": 5, "day": 23, "year": 1950}, "place_of_birth": "Thomasville, Thomas County, Ga.", "post_secondary_degrees": [{"degree": "A.B.", "year": 1970, "institution": "College of William and Mary, Williamsburg, Va."}, {"degree": "M.A.", "year": 1973, "institution": "University of Georgia, Athens, Ga."}, {"degree": "Ph.D.", "year": 1976, "institution": "Florida State University, Tallahassee, Fla."}]}