{"id": "T000250", "update_date": "2019-01-04", "biography_text": "THUNE, John,  a Senator and a Representative from South Dakota; born in Pierre, Hughes County, S. Dak., January 7, 1961; graduated from Jones County High School, S. Dak., 1979; B.S., Biola University, La Mirada, Calif., 1983; M.B.A., University of South Dakota, Vermillion, S. Dak., 1984; executive director, South Dakota state municipal league; board of directors, National League of Cities; staff, United States Senator James Abdnor of South Dakota 1985-1986; South Dakota state Republican party executive director 1989-1991; director, South Dakota state railroad division 1991-1993; director, South Dakota state municipal league 1993-1996; elected as a Republican to the One Hundred Fifth and to the two succeeding Congresses (January 3, 1997-January 3, 2003); was not a candidate for reelection to the One Hundred Eighth Congress in 2002, but was an unsuccessful candidate for the United States Senate; elected as a Republican to the U.S. Senate in 2004; reelected in 2010, and again in 2016 for the term ending January 3, 2023; vice-chair, Republican Conference (2009); chair, Republican Policy Committee (2009-2012); chair, Republican Conference (2012-2018); Republican party whip (2019-); chair, Committee on Commerce, Science, and Transportation (One Hundred Fourteenth and One Hundred Fifteenth Congresses).  ", "name": {"last": "Thune", "first": "John"}, "date_of_birth": {"month": 1, "day": 7, "year": 1961}, "place_of_birth": "Pierre, Hughes County, S. Dak.", "post_secondary_degrees": [{"degree": "B.S.", "year": 1983, "institution": "Biola University, La Mirada, Calif."}, {"degree": "M.B.A.", "year": 1984, "institution": "University of South Dakota, Vermillion, S. Dak."}]}