{"id": "T000472", "update_date": "2018-01-10", "biography_text": "TAKANO, Mark, a Representative from California; born in Riverside, Riverside County, Calif., December 10, 1960; graduated from La Sierra High School, Riverside, Calif., 1979; A.B., Harvard University, Cambridge, Mass., 1983; M.F.A., University of California, Riverside, Calif.; teacher; member of the Riverside Community College district board of trustees, 1990-2012, president, 1992, 1997, 1998, 2005, 2006; unsuccessful candidate for election to the One Hundred Third Congress in 1992 and One Hundred Fourth Congress in 1994; elected as a Democrat to the One Hundred Thirteenth and to the two succeeding Congresses (January 3, 2013-present).", "name": {"last": "Takano", "first": "Mark"}, "date_of_birth": {"month": 12, "day": 10, "year": 1960}, "place_of_birth": "Riverside, Riverside County, Calif.", "post_secondary_degrees": [{"degree": "A.B.", "year": 1983, "institution": "Harvard University, Cambridge, Mass."}, {"degree": "M.F.A.", "institution": "University of California, Riverside, Calif."}]}