{"id": "V000108", "update_date": "2018-12-23", "biography_text": "VISCLOSKY, Peter, a Representative from Indiana; born in Gary, Lake County, Ind., August 13, 1949; graduated from Andrean High School, Merrillville, Ind.; B.S., Indiana University Northwest, Gary, Ind., 1970; J.D., University of Notre Dame School of Law, Notre Dame, Ind., 1973; LL.M., Georgetown University Law Center, Washington, D.C., 1982; lawyer, private practice; staff, United States House of Representatives Committee on Appropriations, 1977-1980; staff, United States House of Representatives Committee on the Budget, 1980-1982; elected as a Democrat to the Ninety-ninth and to the sixteen succeeding Congresses (January 3, 1985-present).", "name": {"last": "Visclosky", "first": "Peter"}, "date_of_birth": {"month": 8, "day": 13, "year": 1949}, "place_of_birth": "Gary, Lake County, Ind.", "post_secondary_degrees": [{"degree": "B.S.", "year": 1970, "institution": "Indiana University Northwest, Gary, Ind."}, {"degree": "J.D.", "year": 1973, "institution": "University of Notre Dame School of Law, Notre Dame, Ind."}]}