{"id": "V000081", "update_date": "2017-12-31", "biography_text": "VEL\u00c1ZQUEZ, Nydia M., a Representative from New York; born in Yabucoa, P.R., March 28, 1953; B.A., University of Puerto Rico, Rio Piedras, 1974; M.A., New York University, New York, N.Y., 1976; faculty, University of Puerto Rico, Humacao, P.R., 1976-1981; adjunct professor, Hunter College, City University of New York, N.Y., 1981-1983; staff, United States Representative Edolphus Towns of New York, 1983; member of the New York, N.Y., city council, 1984; national director, Migration Division Office, Puerto Rico department of labor and human resources, 1986-1989; director, department of Puerto Rican community affairs in the United States for the Commonwealth of Puerto Rico, 1989-1992; elected as a Democrat to the One Hundred Third and to the twelve succeeding Congresses (January 3, 1993-present); chair, Committee on Small Business (One Hundred Tenth and One Hundred Eleventh Congresses).", "name": {"last": "Vel\u00e1zquez", "first": "Nydia", "middle": "M."}, "date_of_birth": {"month": "March", "day": "28", "year": "1953"}, "place_of_birth": "Yabucoa, P.R.", "post_secondary_degrees": [{"degree": "B.A.", "year": "1974", "institution": "University of Puerto Rico, Rio Piedras"}, {"degree": "M.A.", "year": "1976", "institution": "New York University, New York, N.Y."}]}