{"id": "V000133", "update_date": "2019-01-04", "biography_text": "VAN DREW, Jefferson, a Representative from New Jersey; born in New York City, New York County, N.Y., February 23, 1953; attended Eastside High School, Paterson, N.J., and graduated from St. Mary\u00e2\u0080\u0099s High School, Perth Amboy, N.J., 1971; B.S. Rutgers University, New Brunswick, N.J.; D.D.S., Fairleigh Dickinson University, Teaneck, N.J., 1979; dentist; Mayor of Dennis Township, N.J., 1994-1995, 1997-2003; member of the board of chosen freeholders, Cape May County, N.J., 1994-1997; member of the New Jersey general assembly, 2001-2007; member of the New Jersey state senate, 2008-2019; elected as a Democrat to the One Hundred Sixteenth Congress (January 3, 2019-present). ", "name": {"last": "Van drew", "first": "Jefferson"}, "date_of_birth": {"month": 2, "day": 23, "year": 1953}, "place_of_birth": "New York City, New York County, N.Y.", "post_secondary_degrees": [{"degree": "B.S.", "institution": "New Brunswick, N.J."}, {"degree": "D.D.S.", "year": 1979, "institution": "Fairleigh Dickinson University, Teaneck, N.J."}]}