{"id": "V000130", "update_date": "2018-12-23", "biography_text": "VARGAS, Juan, a Representative from California; born in National City, San Diego County, Calif., March 7, 1961; B.A., University of San Diego, San Diego, Calif., 1983; M.A., Fordham University, Bronx, N.Y., 1987; J.D., Harvard University, Cambridge, Mass., 1991; lawyer; business executive; member of the San Diego, Calif., city council, 1993-2000; member of the California state assembly, 2000-2006; member of the California state senate, 2010-2012; unsuccessful candidate for nomination to the One Hundred Third Congress in 1993, the One Hundred Fifth Congress in 1996, and the One Hundred Tenth Congress in 2006; elected as a Democrat to the One Hundred Thirteenth and to the two succeeding Congresses (January 3, 2013-present).", "name": {"last": "Vargas", "first": "Juan"}, "date_of_birth": {"month": 3, "day": 7, "year": 1961}, "place_of_birth": "National City, San Diego County, Calif.", "post_secondary_degrees": [{"degree": "B.A.", "year": 1983, "institution": "University of San Diego, San Diego, Calif."}, {"degree": "M.A.", "year": 1987, "institution": "Fordham University, Bronx, N.Y."}, {"degree": "J.D.", "year": 1991, "institution": "Harvard University, Cambridge, Mass."}]}