{"id": "W000798", "update_date": "2018-01-10", "biography_text": "WALBERG, Tim, a Representative from Michigan; born in Chicago, Cook County, Ill., April 12, 1951; graduated from Thornton Fractional Township North High School, Calumet, Ill., 1969; attended Western Illinois University, Macomb, Ill., 1969-1970; attended Moody Bible College Institute, Chicago, Ill., 1970-1973; B.S., Fort Wayne Bible College, Fort Wayne., Ind., 1975; M.A., Wheaton College, Wheaton, Ill., 1978; minister; member of the Michigan state house of representatives, 1983-1998; unsuccessful candidate for nomination to the One Hundred Ninth Congress in 2004; elected as a Republican to the One Hundred Tenth Congress (January 3, 2007-January 3, 2009); unsuccessful candidate for reelection to the One Hundred Eleventh Congress in 2008; elected as a Republican to the One Hundred Twelfth and to the three succeeding Congresses (January 3, 2011-present).", "name": {"last": "Walberg", "first": "Tim"}, "date_of_birth": {"month": 4, "day": 12, "year": 1951}, "place_of_birth": "Chicago, Cook County, Ill.", "post_secondary_degrees": [{"degree": "B.S.", "year": 1975, "institution": "Fort Wayne Bible College, Fort Wayne., Ind."}, {"degree": "M.A.", "year": 1978, "institution": "Wheaton College, Wheaton, Ill."}]}