{"id": "W000804", "update_date": "2018-01-10", "biography_text": "WITTMAN, Robert J., a Representative from Virginia; born in Washington, D.C., February 3, 1959; B.S., Virginia Polytechnic Institute, Blacksburg, Va., 1981; M.P.H., University of North Carolina, Chapel Hill, N.C., 1990; Ph.D., Virginia Commonwealth University, Richmond, Va., 2002; shellfish sanitation; member of the Montross, Va., town council, 1986-1996; Mayor of Montross, Va., 1992-1996; member of the Westmoreland County, Va., board of supervisors, 1996-2005; chairman of the Westmoreland County Va., board of supervisors, 2004-2005; member of the Virginia house of delegates, 2006-2007; elected as a Republican to the One Hundred Tenth Congress, by special election, to fill the vacancy caused by the death of United States Representative Jo Ann Davis, and to the five succeeding Congresses (December 11, 2007-present).", "name": {"last": "Wittman", "first": "Robert", "middle": "J."}, "date_of_birth": {"month": "February", "day": "3", "year": "1959"}, "place_of_birth": "Washington, D.C.", "post_secondary_degrees": [{"degree": "B.S.", "year": "1981", "institution": "Virginia Polytechnic Institute, Blacksburg, Va."}, {"degree": "M.P.H.", "year": "1990", "institution": "University of North Carolina, Chapel Hill, N.C."}, {"degree": "Ph.D.", "year": "2002", "institution": "Virginia Commonwealth University, Richmond, Va."}]}