{"id": "Z000017", "update_date": "2018-12-23", "biography_text": "ZELDIN, Lee M, a Representative from New York; born in East Meadow, Nassau County, N.Y., January 30, 1980; graduated from William Floyd High School, Brookhaven, N.Y., 1998; B.A., State University of New York, Albany, N.Y., 2001; J.D., Albany Law School, Albany, N.Y., 2003; United States Army, 2003-2007; United States Army Reserve, 2007-present; lawyer, private practice; unsuccessful candidate for election to the One Hundred Eleventh Congress in 2008; member of the New York state senate, 2011-2014; elected as a Republican to the One Hundred Fourteenth and to the succeeding Congress (January 3, 2015-present).", "name": {"last": "Zeldin", "first": "Lee", "middle": "M"}, "date_of_birth": {"month": 1, "day": 30, "year": 1980}, "place_of_birth": "East Meadow, Nassau County, N.Y.", "post_secondary_degrees": [{"degree": "B.A.", "year": 2001, "institution": "State University of New York, Albany, N.Y."}, {"degree": "J.D.", "year": 2003, "institution": "Albany Law School, Albany, N.Y."}]}