{"id": "Z000018", "update_date": "2018-12-23", "biography_text": "ZINKE, Ryan, a Representative from Montana; born in Bozeman, Gallatin County, Mont., November 1, 1961; graduated from Whitefish High School, Whitefish, Mont., 1980; B.S., University of Oregon, Eugene, Ore., 1984; M.B.A., National University, San Diego, Calif., 1991; M.S., University of San Diego, Calif., 2003; United States Navy, 1985-2008; business executive; member of the Montana state senate, 2009-2012; unsuccessful candidate for nomination for lieutenant governor of Montana in 2012; elected as a Republican to the One Hundred Fourteenth and to the succeeding Congress until his resignation on March 1, 2017 (January 3, 2015-March 1, 2017); Secretary of the Interior in the Cabinet of President Donald J. Trump, 2017-present.", "name": {"last": "Zinke", "first": "Ryan"}, "date_of_birth": {"month": 11, "day": 1, "year": 1961}, "place_of_birth": "Bozeman, Gallatin County, Mont.", "post_secondary_degrees": [{"degree": "B.S.", "year": 1984, "institution": "University of Oregon, Eugene, Ore."}, {"degree": "M.B.A.", "year": 1991, "institution": "National University, San Diego, Calif."}, {"degree": "M.S.", "year": 2003, "institution": "University of San Diego, Calif."}]}